[
  {
    "名前": "ARシステム",
    "威力補正": "",
    "攻撃補正": "",
    "はりきり補正": "",
    "おやこあい補正": "",
    "防御補正": "",
    "その他の補正": "",
    "Mhalf": "",
    "Mfilter": "",
    "効果": "持たせたメモリによってフォルムとタイプが変わる。"
  },
  {
    "名前": "アイスフェイス",
    "威力補正": "",
    "攻撃補正": "",
    "はりきり補正": "",
    "おやこあい補正": "",
    "防御補正": "",
    "その他の補正": "",
    "Mhalf": "",
    "Mfilter": "",
    "効果": "物理技を受けると、ダメージを無効化してフォルムチェンジする。天気があられ/ゆき状態に変わるとフォルムが戻る。"
  },
  {
    "名前": "アイスボディ",
    "威力補正": "",
    "攻撃補正": "",
    "はりきり補正": "",
    "おやこあい補正": "",
    "防御補正": "",
    "その他の補正": "",
    "Mhalf": "",
    "Mfilter": "",
    "効果": "あられ/ゆきのとき、HPが1/16回復する。"
  },
  {
    "名前": "あくしゅう",
    "威力補正": "",
    "攻撃補正": "",
    "はりきり補正": "",
    "おやこあい補正": "",
    "防御補正": "",
    "その他の補正": "",
    "Mhalf": "",
    "Mfilter": "",
    "効果": "攻撃した相手をひるませることがある。"
  },
  {
    "名前": "あついしぼう",
    "威力補正": "",
    "攻撃補正": "攻撃補正",
    "はりきり補正": "",
    "おやこあい補正": "",
    "防御補正": "",
    "その他の補正": "",
    "Mhalf": "",
    "Mfilter": "",
    "効果": "自分がほのお・こおりわざを受ける時の相手のこうげき・とくこうを半減させる。"
  },
  {
    "名前": "あとだし",
    "威力補正": "",
    "攻撃補正": "",
    "はりきり補正": "",
    "おやこあい補正": "",
    "防御補正": "",
    "その他の補正": "",
    "Mhalf": "",
    "Mfilter": "",
    "効果": "自分の行動順が、同じ優先度の中で最後になる。"
  },
  {
    "名前": "アナライズ",
    "威力補正": "威力補正",
    "攻撃補正": "",
    "はりきり補正": "",
    "おやこあい補正": "",
    "防御補正": "",
    "その他の補正": "",
    "Mhalf": "",
    "Mfilter": "",
    "効果": "最後にわざを出すと威力が1.3倍になる。"
  },
  {
    "名前": "あまのじゃく",
    "威力補正": "",
    "攻撃補正": "",
    "はりきり補正": "",
    "おやこあい補正": "",
    "防御補正": "",
    "その他の補正": "",
    "Mhalf": "",
    "Mfilter": "",
    "効果": "自分にかかるランク補正を逆にする。"
  },
  {
    "名前": "あめうけざら",
    "威力補正": "",
    "攻撃補正": "",
    "はりきり補正": "",
    "おやこあい補正": "",
    "防御補正": "",
    "その他の補正": "",
    "Mhalf": "",
    "Mfilter": "",
    "効果": "あめのとき、HPが1/16回復する。"
  },
  {
    "名前": "あめふらし",
    "威力補正": "",
    "攻撃補正": "",
    "はりきり補正": "",
    "おやこあい補正": "",
    "防御補正": "",
    "その他の補正": "",
    "Mhalf": "",
    "Mfilter": "",
    "効果": "場に出たとき、てんきをあめ状態にする。"
  },
  {
    "名前": "ありじごく",
    "威力補正": "",
    "攻撃補正": "",
    "はりきり補正": "",
    "おやこあい補正": "",
    "防御補正": "",
    "その他の補正": "",
    "Mhalf": "",
    "Mfilter": "",
    "効果": "相手を逃げられなくする。"
  },
  {
    "名前": "アロマベール",
    "威力補正": "",
    "攻撃補正": "",
    "はりきり補正": "",
    "おやこあい補正": "",
    "防御補正": "",
    "その他の補正": "",
    "Mhalf": "",
    "Mfilter": "",
    "効果": "自分と味方がメンタル系の状態変化にならない。"
  },
  {
    "名前": "いかく",
    "威力補正": "",
    "攻撃補正": "",
    "はりきり補正": "",
    "おやこあい補正": "",
    "防御補正": "",
    "その他の補正": "",
    "Mhalf": "",
    "Mfilter": "",
    "効果": "場に出たときに、相手のこうげきを1段階下げる。"
  },
  {
    "名前": "いかりのこうら",
    "威力補正": "",
    "攻撃補正": "",
    "はりきり補正": "",
    "おやこあい補正": "",
    "防御補正": "",
    "その他の補正": "",
    "Mhalf": "",
    "Mfilter": "",
    "効果": "HPが半分以下になったとき、ぼうぎょ・とくぼうが1段階下がり、こうげき・とくこう・すばやさが1段階上がる。"
  },
  {
    "名前": "いかりのつぼ",
    "威力補正": "",
    "攻撃補正": "",
    "はりきり補正": "",
    "おやこあい補正": "",
    "防御補正": "",
    "その他の補正": "",
    "Mhalf": "",
    "Mfilter": "",
    "効果": "急所に当たると、攻撃が最大まで上がる。"
  },
  {
    "名前": "いしあたま",
    "威力補正": "",
    "攻撃補正": "",
    "はりきり補正": "",
    "おやこあい補正": "",
    "防御補正": "",
    "その他の補正": "",
    "Mhalf": "",
    "Mfilter": "",
    "効果": "反動技を使用してもダメージを受けない。"
  },
  {
    "名前": "いたずらごころ",
    "威力補正": "",
    "攻撃補正": "",
    "はりきり補正": "",
    "おやこあい補正": "",
    "防御補正": "",
    "その他の補正": "",
    "Mhalf": "",
    "Mfilter": "",
    "効果": "変化技の優先度を1高くして出せる。"
  },
  {
    "名前": "いやしのこころ",
    "威力補正": "",
    "攻撃補正": "",
    "はりきり補正": "",
    "おやこあい補正": "",
    "防御補正": "",
    "その他の補正": "",
    "Mhalf": "",
    "Mfilter": "",
    "効果": "味方の状態異常を治すことがある。"
  },
  {
    "名前": "イリュージョン",
    "威力補正": "",
    "攻撃補正": "",
    "はりきり補正": "",
    "おやこあい補正": "",
    "防御補正": "",
    "その他の補正": "",
    "Mhalf": "",
    "Mfilter": "",
    "効果": "手持ちのポケモンに化けて場に出る。"
  },
  {
    "名前": "いろめがね",
    "威力補正": "",
    "攻撃補正": "",
    "はりきり補正": "",
    "おやこあい補正": "",
    "防御補正": "",
    "その他の補正": "いろめがね補正",
    "Mhalf": "",
    "Mfilter": "",
    "効果": "与える「効果は 今ひとつ」のダメージが2倍になる。"
  },
  {
    "名前": "いわはこび",
    "威力補正": "",
    "攻撃補正": "攻撃補正",
    "はりきり補正": "",
    "おやこあい補正": "",
    "防御補正": "",
    "その他の補正": "",
    "Mhalf": "",
    "Mfilter": "",
    "効果": "いわタイプの技で攻撃するとき、こうげき・とくこうが1.5倍になる。"
  },
  {
    "名前": "うのミサイル",
    "威力補正": "",
    "攻撃補正": "",
    "はりきり補正": "",
    "おやこあい補正": "",
    "防御補正": "",
    "その他の補正": "",
    "Mhalf": "",
    "Mfilter": "",
    "効果": "なみのりかダイビングを使うと水中から獲物を咥えてくる。この状態で攻撃を受けると咥えた獲物を吐き出して反撃し、元のフォルムに戻る。"
  },
  {
    "名前": "うるおいボイス",
    "威力補正": "",
    "攻撃補正": "",
    "はりきり補正": "",
    "おやこあい補正": "",
    "防御補正": "",
    "その他の補正": "",
    "Mhalf": "",
    "Mfilter": "",
    "効果": "音のわざがみずタイプになる。"
  },
  {
    "名前": "うるおいボディ",
    "威力補正": "",
    "攻撃補正": "",
    "はりきり補正": "",
    "おやこあい補正": "",
    "防御補正": "",
    "その他の補正": "",
    "Mhalf": "",
    "Mfilter": "",
    "効果": "あめのとき、状態異常を治す。"
  },
  {
    "名前": "エアロック",
    "威力補正": "",
    "攻撃補正": "",
    "はりきり補正": "",
    "おやこあい補正": "",
    "防御補正": "",
    "その他の補正": "",
    "Mhalf": "",
    "Mfilter": "",
    "効果": "天気の影響が無くなる。"
  },
  {
    "名前": "エレキスキン",
    "威力補正": "威力補正",
    "攻撃補正": "",
    "はりきり補正": "",
    "おやこあい補正": "",
    "防御補正": "",
    "その他の補正": "",
    "Mhalf": "",
    "Mfilter": "",
    "効果": "ノーマルタイプのわざがでんきタイプになり、威力が1.2倍になる。"
  },
  {
    "名前": "エレキメイカー",
    "威力補正": "",
    "攻撃補正": "",
    "はりきり補正": "",
    "おやこあい補正": "",
    "防御補正": "",
    "その他の補正": "",
    "Mhalf": "",
    "Mfilter": "",
    "効果": "場の状態をエレキフィールドにする。"
  },
  {
    "名前": "えんかく",
    "威力補正": "",
    "攻撃補正": "",
    "はりきり補正": "",
    "おやこあい補正": "",
    "防御補正": "",
    "その他の補正": "",
    "Mhalf": "",
    "Mfilter": "",
    "効果": "使用する直接攻撃わざが、直接攻撃でなくなる。"
  },
  {
    "名前": "おうごんのからだ",
    "威力補正": "",
    "攻撃補正": "",
    "はりきり補正": "",
    "おやこあい補正": "",
    "防御補正": "",
    "その他の補正": "",
    "Mhalf": "",
    "Mfilter": "",
    "効果": "他のポケモンから受ける変化技を無効化する。"
  },
  {
    "名前": "オーラブレイク",
    "威力補正": "威力補正",
    "攻撃補正": "",
    "はりきり補正": "",
    "おやこあい補正": "",
    "防御補正": "",
    "その他の補正": "",
    "Mhalf": "",
    "Mfilter": "",
    "効果": "ダークオーラ・フェアリーオーラの効果を逆にし、威力が0.75倍になるようにする。"
  },
  {
    "名前": "おどりこ",
    "威力補正": "",
    "攻撃補正": "",
    "はりきり補正": "",
    "おやこあい補正": "",
    "防御補正": "",
    "その他の補正": "",
    "Mhalf": "",
    "Mfilter": "",
    "効果": "他のポケモンが踊り系のわざを使った直後に同じ技をだす。"
  },
  {
    "名前": "おみとおし",
    "威力補正": "",
    "攻撃補正": "",
    "はりきり補正": "",
    "おやこあい補正": "",
    "防御補正": "",
    "その他の補正": "",
    "Mhalf": "",
    "Mfilter": "",
    "効果": "相手の持ち物が分かる。"
  },
  {
    "名前": "おもかげやどし",
    "威力補正": "",
    "攻撃補正": "",
    "はりきり補正": "",
    "おやこあい補正": "",
    "防御補正": "",
    "その他の補正": "",
    "Mhalf": "",
    "Mfilter": "",
    "効果": "オーガポン (みどりのめん) がテラスタルしたとき、すばやさが1段階上がる。"
  },
  {
    "名前": "おもかげやどし",
    "威力補正": "",
    "攻撃補正": "",
    "はりきり補正": "",
    "おやこあい補正": "",
    "防御補正": "",
    "その他の補正": "",
    "Mhalf": "",
    "Mfilter": "",
    "効果": "オーガポン (かまどのめん) がテラスタルしたとき、こうげきが1段階上がる。"
  },
  {
    "名前": "おもかげやどし",
    "威力補正": "",
    "攻撃補正": "",
    "はりきり補正": "",
    "おやこあい補正": "",
    "防御補正": "",
    "その他の補正": "",
    "Mhalf": "",
    "Mfilter": "",
    "効果": "オーガポン (いどのめん) がテラスタルしたとき、とくぼうが1段階上がる。"
  },
  {
    "名前": "おもかげやどし",
    "威力補正": "",
    "攻撃補正": "",
    "はりきり補正": "",
    "おやこあい補正": "",
    "防御補正": "",
    "その他の補正": "",
    "Mhalf": "",
    "Mfilter": "",
    "効果": "オーガポン (いしずえのめん) がテラスタルしたとき、ぼうぎょが1段階上がる。"
  },
  {
    "名前": "おもてなし",
    "威力補正": "",
    "攻撃補正": "",
    "はりきり補正": "",
    "おやこあい補正": "",
    "防御補正": "",
    "その他の補正": "",
    "Mhalf": "",
    "Mfilter": "",
    "効果": "場に出たとき、味方のHPを1/4回復する。"
  },
  {
    "名前": "おやこあい",
    "威力補正": "",
    "攻撃補正": "",
    "はりきり補正": "",
    "おやこあい補正": "おやこあい補正",
    "防御補正": "",
    "その他の補正": "",
    "Mhalf": "",
    "Mfilter": "",
    "効果": "攻撃技を出した際に、25%の威力の2発目を出せる。"
  },
  {
    "名前": "おわりのだいち",
    "威力補正": "",
    "攻撃補正": "",
    "はりきり補正": "",
    "おやこあい補正": "",
    "防御補正": "",
    "その他の補正": "",
    "Mhalf": "",
    "Mfilter": "",
    "効果": "天気をおおひでりにする。"
  },
  {
    "名前": "カーリーヘアー",
    "威力補正": "",
    "攻撃補正": "",
    "はりきり補正": "",
    "おやこあい補正": "",
    "防御補正": "",
    "その他の補正": "",
    "Mhalf": "",
    "Mfilter": "",
    "効果": "直接攻撃を受けたとき、相手のすばやさを1段階下げる。"
  },
  {
    "名前": "かいりきバサミ",
    "威力補正": "",
    "攻撃補正": "",
    "はりきり補正": "",
    "おやこあい補正": "",
    "防御補正": "",
    "その他の補正": "",
    "Mhalf": "",
    "Mfilter": "",
    "効果": "相手からこうげきを下げられない。"
  },
  {
    "名前": "かがくのちから",
    "威力補正": "",
    "攻撃補正": "",
    "はりきり補正": "",
    "おやこあい補正": "",
    "防御補正": "",
    "その他の補正": "",
    "Mhalf": "",
    "Mfilter": "",
    "効果": "味方がひんしになったとき、そのポケモンと同じ特性になる。"
  },
  {
    "名前": "かがくへんかガス",
    "威力補正": "",
    "攻撃補正": "",
    "はりきり補正": "",
    "おやこあい補正": "",
    "防御補正": "",
    "その他の補正": "",
    "Mhalf": "",
    "Mfilter": "",
    "効果": "場にいる間、他の特性の効果が発動しなくなる。"
  },
  {
    "名前": "かげふみ",
    "威力補正": "",
    "攻撃補正": "",
    "はりきり補正": "",
    "おやこあい補正": "",
    "防御補正": "",
    "その他の補正": "",
    "Mhalf": "",
    "Mfilter": "",
    "効果": "相手を逃げられなくする。"
  },
  {
    "名前": "かぜのり",
    "威力補正": "",
    "攻撃補正": "",
    "はりきり補正": "",
    "おやこあい補正": "",
    "防御補正": "",
    "その他の補正": "",
    "Mhalf": "",
    "Mfilter": "",
    "効果": "おいかぜ状態の効果を受けるか、風の技を受けるとこうげきが1段階上がる。風の技のダメージを受けない。"
  },
  {
    "名前": "かそく",
    "威力補正": "",
    "攻撃補正": "",
    "はりきり補正": "",
    "おやこあい補正": "",
    "防御補正": "",
    "その他の補正": "",
    "Mhalf": "",
    "Mfilter": "",
    "効果": "毎ターンすばやさが1段階上がる。"
  },
  {
    "名前": "かたいツメ",
    "威力補正": "威力補正",
    "攻撃補正": "",
    "はりきり補正": "",
    "おやこあい補正": "",
    "防御補正": "",
    "その他の補正": "",
    "Mhalf": "",
    "Mfilter": "",
    "効果": "使用する直接攻撃の威力が1.3倍になる。"
  },
  {
    "名前": "かたやぶり",
    "威力補正": "",
    "攻撃補正": "",
    "はりきり補正": "",
    "おやこあい補正": "",
    "防御補正": "",
    "その他の補正": "",
    "Mhalf": "",
    "Mfilter": "",
    "効果": "特性の影響を受けずに技を出せる。"
  },
  {
    "名前": "かちき",
    "威力補正": "",
    "攻撃補正": "",
    "はりきり補正": "",
    "おやこあい補正": "",
    "防御補正": "",
    "その他の補正": "",
    "Mhalf": "",
    "Mfilter": "",
    "効果": "敵から能力を下げられたとき、とくこうが2段階上がる。"
  },
  {
    "名前": "カブトアーマー",
    "威力補正": "",
    "攻撃補正": "",
    "はりきり補正": "",
    "おやこあい補正": "",
    "防御補正": "",
    "その他の補正": "",
    "Mhalf": "",
    "Mfilter": "",
    "効果": "相手の攻撃が急所に当たらない。"
  },
  {
    "名前": "かるわざ",
    "威力補正": "",
    "攻撃補正": "",
    "はりきり補正": "",
    "おやこあい補正": "",
    "防御補正": "",
    "その他の補正": "",
    "Mhalf": "",
    "Mfilter": "",
    "効果": "道具を持っていないとすばやさが2倍になる。"
  },
  {
    "名前": "かわりもの",
    "威力補正": "",
    "攻撃補正": "",
    "はりきり補正": "",
    "おやこあい補正": "",
    "防御補正": "",
    "その他の補正": "",
    "Mhalf": "",
    "Mfilter": "",
    "効果": "場に出た直後に相手にへんしんする。"
  },
  {
    "名前": "がんじょう",
    "威力補正": "",
    "攻撃補正": "",
    "はりきり補正": "",
    "おやこあい補正": "",
    "防御補正": "",
    "その他の補正": "",
    "Mhalf": "",
    "Mfilter": "",
    "効果": "一撃必殺技が効かない。HPが満タンならば一撃でひんしになるダメージでもHP1で持ちこたえる。"
  },
  {
    "名前": "がんじょうあご",
    "威力補正": "威力補正",
    "攻撃補正": "",
    "はりきり補正": "",
    "おやこあい補正": "",
    "防御補正": "",
    "その他の補正": "",
    "Mhalf": "",
    "Mfilter": "",
    "効果": "かみつきわざの威力が1.5倍になる。"
  },
  {
    "名前": "かんそうはだ",
    "威力補正": "威力補正",
    "攻撃補正": "",
    "はりきり補正": "",
    "おやこあい補正": "",
    "防御補正": "",
    "その他の補正": "みず無効",
    "Mhalf": "",
    "Mfilter": "",
    "効果": "みずわざを受けるとHPが1/4回復し、ほのおわざを受けた時の威力は1.25倍になる。あめのときはHPを1/8回復し、にほんばれのときは1/8のダメージを受ける。"
  },
  {
    "名前": "かんろなミツ",
    "威力補正": "",
    "攻撃補正": "",
    "はりきり補正": "",
    "おやこあい補正": "",
    "防御補正": "",
    "その他の補正": "",
    "Mhalf": "",
    "Mfilter": "",
    "効果": "場に出たとき、相手の回避率を1段階下げる。"
  },
  {
    "名前": "ききかいひ",
    "威力補正": "",
    "攻撃補正": "",
    "はりきり補正": "",
    "おやこあい補正": "",
    "防御補正": "",
    "その他の補正": "",
    "Mhalf": "",
    "Mfilter": "",
    "効果": "HPが半分以下になると交代する。"
  },
  {
    "名前": "きけんよち",
    "威力補正": "",
    "攻撃補正": "",
    "はりきり補正": "",
    "おやこあい補正": "",
    "防御補正": "",
    "その他の補正": "",
    "Mhalf": "",
    "Mfilter": "",
    "効果": "相手が自分に効果抜群のわざを持っているかわかる。"
  },
  {
    "名前": "きずなへんげ",
    "威力補正": "",
    "攻撃補正": "",
    "はりきり補正": "",
    "おやこあい補正": "",
    "防御補正": "",
    "その他の補正": "",
    "Mhalf": "",
    "Mfilter": "",
    "効果": "ポケモンを倒すとこうげき・とくこう・すばやさが1段階ずつ上昇する。"
  },
  {
    "名前": "ぎたい",
    "威力補正": "",
    "攻撃補正": "",
    "はりきり補正": "",
    "おやこあい補正": "",
    "防御補正": "",
    "その他の補正": "",
    "Mhalf": "",
    "Mfilter": "",
    "効果": "フィールドに合わせてタイプが変わる。"
  },
  {
    "名前": "きみょうなくすり",
    "威力補正": "",
    "攻撃補正": "",
    "はりきり補正": "",
    "おやこあい補正": "",
    "防御補正": "",
    "その他の補正": "",
    "Mhalf": "",
    "Mfilter": "",
    "効果": "場に出たとき、味方のランク補正を元に戻す。"
  },
  {
    "名前": "きもったま",
    "威力補正": "",
    "攻撃補正": "",
    "はりきり補正": "",
    "おやこあい補正": "",
    "防御補正": "",
    "その他の補正": "",
    "Mhalf": "",
    "Mfilter": "",
    "効果": "ゴーストタイプにノーマル・かくとうわざが当たるようになる。"
  },
  {
    "名前": "ぎゃくじょう",
    "威力補正": "",
    "攻撃補正": "",
    "はりきり補正": "",
    "おやこあい補正": "",
    "防御補正": "",
    "その他の補正": "",
    "Mhalf": "",
    "Mfilter": "",
    "効果": "HPが半分以下になったとき、とくこうが1段階上がる。"
  },
  {
    "名前": "きゅうばん",
    "威力補正": "",
    "攻撃補正": "",
    "はりきり補正": "",
    "おやこあい補正": "",
    "防御補正": "",
    "その他の補正": "",
    "Mhalf": "",
    "Mfilter": "",
    "効果": "相手の交代させる技やレッドカードの効果を受けない。"
  },
  {
    "名前": "きょううん",
    "威力補正": "",
    "攻撃補正": "",
    "はりきり補正": "",
    "おやこあい補正": "",
    "防御補正": "",
    "その他の補正": "",
    "Mhalf": "",
    "Mfilter": "",
    "効果": "急所ランクが1段階上がる。"
  },
  {
    "名前": "きょうえん",
    "威力補正": "",
    "攻撃補正": "",
    "はりきり補正": "",
    "おやこあい補正": "",
    "防御補正": "",
    "その他の補正": "",
    "Mhalf": "",
    "Mfilter": "",
    "効果": "場に出たとき、味方のランク補正をコピーする。"
  },
  {
    "名前": "きょうせい",
    "威力補正": "",
    "攻撃補正": "",
    "はりきり補正": "",
    "おやこあい補正": "",
    "防御補正": "",
    "その他の補正": "",
    "Mhalf": "",
    "Mfilter": "",
    "効果": "味方の持ち物がなくなったとき、自分の持ち物を渡す。"
  },
  {
    "名前": "ぎょぐん",
    "威力補正": "",
    "攻撃補正": "",
    "はりきり補正": "",
    "おやこあい補正": "",
    "防御補正": "",
    "その他の補正": "",
    "Mhalf": "",
    "Mfilter": "",
    "効果": "HPが25%以上あるとヨワシのフォルムが変化する。"
  },
  {
    "名前": "きよめのしお",
    "威力補正": "",
    "攻撃補正": "攻撃補正",
    "はりきり補正": "",
    "おやこあい補正": "",
    "防御補正": "",
    "その他の補正": "",
    "Mhalf": "",
    "Mfilter": "",
    "効果": "状態異常にならず、ゴースト技を受けるとき相手のこうげき・とくこうを半減させる。"
  },
  {
    "名前": "きれあじ",
    "威力補正": "威力補正",
    "攻撃補正": "",
    "はりきり補正": "",
    "おやこあい補正": "",
    "防御補正": "",
    "その他の補正": "",
    "Mhalf": "",
    "Mfilter": "",
    "効果": "切る技の威力が1.5倍になる。"
  },
  {
    "名前": "きんしのちから",
    "威力補正": "",
    "攻撃補正": "",
    "はりきり補正": "",
    "おやこあい補正": "",
    "防御補正": "",
    "その他の補正": "",
    "Mhalf": "",
    "Mfilter": "",
    "効果": "変化技を使用するとき、同じ優先度の中で最後に行動するが、相手の特性を無視する。"
  },
  {
    "名前": "きんちょうかん",
    "威力補正": "",
    "攻撃補正": "",
    "はりきり補正": "",
    "おやこあい補正": "",
    "防御補正": "",
    "その他の補正": "",
    "Mhalf": "",
    "Mfilter": "",
    "効果": "相手のきのみを使えなくする。"
  },
  {
    "名前": "くいしんぼう",
    "威力補正": "",
    "攻撃補正": "",
    "はりきり補正": "",
    "おやこあい補正": "",
    "防御補正": "",
    "その他の補正": "",
    "Mhalf": "",
    "Mfilter": "",
    "効果": "きのみを通常より早いタイミングで使う。"
  },
  {
    "名前": "クイックドロウ",
    "威力補正": "",
    "攻撃補正": "",
    "はりきり補正": "",
    "おやこあい補正": "",
    "防御補正": "",
    "その他の補正": "",
    "Mhalf": "",
    "Mfilter": "",
    "効果": "攻撃技を使ったとき、同じ優先度の中で最初に行動できることがある。"
  },
  {
    "名前": "クォークチャージ",
    "威力補正": "",
    "攻撃補正": "攻撃補正",
    "はりきり補正": "",
    "おやこあい補正": "",
    "防御補正": "防御補正",
    "その他の補正": "",
    "Mhalf": "",
    "Mfilter": "",
    "効果": "場がエレキフィールド状態か、ブーストエナジーを持っているとき、自分の最も高い能力が上がる。"
  },
  {
    "名前": "くさのけがわ",
    "威力補正": "",
    "攻撃補正": "",
    "はりきり補正": "",
    "おやこあい補正": "",
    "防御補正": "防御補正",
    "その他の補正": "",
    "Mhalf": "",
    "Mfilter": "",
    "効果": "グラスフィールドのとき、ぼうぎょが1.5倍になる。"
  },
  {
    "名前": "くだけるよろい",
    "威力補正": "",
    "攻撃補正": "",
    "はりきり補正": "",
    "おやこあい補正": "",
    "防御補正": "",
    "その他の補正": "",
    "Mhalf": "",
    "Mfilter": "",
    "効果": "物理技を受けると、ぼうぎょが1段階下がりすばやさが2段階上がる。"
  },
  {
    "名前": "グラスメイカー",
    "威力補正": "",
    "攻撃補正": "",
    "はりきり補正": "",
    "おやこあい補正": "",
    "防御補正": "",
    "その他の補正": "",
    "Mhalf": "",
    "Mfilter": "",
    "効果": "場の状態をグラスフィールドにする。"
  },
  {
    "名前": "クリアボディ",
    "威力補正": "",
    "攻撃補正": "",
    "はりきり補正": "",
    "おやこあい補正": "",
    "防御補正": "",
    "その他の補正": "",
    "Mhalf": "",
    "Mfilter": "",
    "効果": "相手からランク補正を下げられない。"
  },
  {
    "名前": "くろのいななき",
    "威力補正": "",
    "攻撃補正": "",
    "はりきり補正": "",
    "おやこあい補正": "",
    "防御補正": "",
    "その他の補正": "",
    "Mhalf": "",
    "Mfilter": "",
    "効果": "ポケモンを倒すととくこうが1段階上がる。"
  },
  {
    "名前": "げきりゅう",
    "威力補正": "",
    "攻撃補正": "攻撃補正",
    "はりきり補正": "",
    "おやこあい補正": "",
    "防御補正": "",
    "その他の補正": "",
    "Mhalf": "",
    "Mfilter": "",
    "効果": "HPが1/3以下になると、みずタイプのわざで攻撃するときのこうげき・とくこうが1.5倍になる。"
  },
  {
    "名前": "こおりのりんぷん",
    "威力補正": "",
    "攻撃補正": "",
    "はりきり補正": "",
    "おやこあい補正": "",
    "防御補正": "",
    "その他の補正": "",
    "Mhalf": "Mhalf",
    "Mfilter": "",
    "効果": "受ける特殊技のダメージが半減する。"
  },
  {
    "名前": "こだいかっせい",
    "威力補正": "",
    "攻撃補正": "攻撃補正",
    "はりきり補正": "",
    "おやこあい補正": "",
    "防御補正": "防御補正",
    "その他の補正": "",
    "Mhalf": "",
    "Mfilter": "",
    "効果": "場がにほんばれ状態か、ブーストエナジーを持っているとき、自分の最も高い能力が上がる。"
  },
  {
    "名前": "こぼれダネ",
    "威力補正": "",
    "攻撃補正": "",
    "はりきり補正": "",
    "おやこあい補正": "",
    "防御補正": "",
    "その他の補正": "",
    "Mhalf": "",
    "Mfilter": "",
    "効果": "攻撃技を受けたとき、場をグラスフィールド状態にする。"
  },
  {
    "名前": "ごりむちゅう",
    "威力補正": "",
    "攻撃補正": "攻撃補正",
    "はりきり補正": "",
    "おやこあい補正": "",
    "防御補正": "",
    "その他の補正": "",
    "Mhalf": "",
    "Mfilter": "",
    "効果": "こうげきが1.5倍になるが、最初に選んだ技しか出せなくなる。"
  },
  {
    "名前": "こんがりボディ",
    "威力補正": "",
    "攻撃補正": "",
    "はりきり補正": "",
    "おやこあい補正": "",
    "防御補正": "",
    "その他の補正": "",
    "Mhalf": "",
    "Mfilter": "",
    "効果": "ほのおタイプの技を受けても無効化し、ぼうぎょを2段階上げる。"
  },
  {
    "名前": "こんじょう",
    "威力補正": "",
    "攻撃補正": "攻撃補正",
    "はりきり補正": "",
    "おやこあい補正": "",
    "防御補正": "",
    "その他の補正": "",
    "Mhalf": "",
    "Mfilter": "",
    "効果": "状態異常のとき、こうげきが1.5倍になる。"
  },
  {
    "名前": "サーフテール",
    "威力補正": "",
    "攻撃補正": "",
    "はりきり補正": "",
    "おやこあい補正": "",
    "防御補正": "",
    "その他の補正": "",
    "Mhalf": "",
    "Mfilter": "",
    "効果": "場がエレキフィールドのとき、すばやさが2倍になる。"
  },
  {
    "名前": "サイコメイカー",
    "威力補正": "",
    "攻撃補正": "",
    "はりきり補正": "",
    "おやこあい補正": "",
    "防御補正": "",
    "その他の補正": "",
    "Mhalf": "",
    "Mfilter": "",
    "効果": "場の状態をサイコフィールドにする。"
  },
  {
    "名前": "さいせいりょく",
    "威力補正": "",
    "攻撃補正": "",
    "はりきり補正": "",
    "おやこあい補正": "",
    "防御補正": "",
    "その他の補正": "",
    "Mhalf": "",
    "Mfilter": "",
    "効果": "手持ちに戻るとHPが1/3回復する。"
  },
  {
    "名前": "さまようたましい",
    "威力補正": "",
    "攻撃補正": "",
    "はりきり補正": "",
    "おやこあい補正": "",
    "防御補正": "",
    "その他の補正": "",
    "Mhalf": "",
    "Mfilter": "",
    "効果": "直接攻撃を受けたとき、相手と特性を入れ替える。"
  },
  {
    "名前": "さめはだ",
    "威力補正": "",
    "攻撃補正": "",
    "はりきり補正": "",
    "おやこあい補正": "",
    "防御補正": "",
    "その他の補正": "",
    "Mhalf": "",
    "Mfilter": "",
    "効果": "直接攻撃を受けたとき、相手に最大HPの1/8分のダメージを与える。"
  },
  {
    "名前": "サンパワー",
    "威力補正": "",
    "攻撃補正": "攻撃補正",
    "はりきり補正": "",
    "おやこあい補正": "",
    "防御補正": "",
    "その他の補正": "",
    "Mhalf": "",
    "Mfilter": "",
    "効果": "にほんばれのとき、毎ターンHPが1/8減り、とくこうが1.5倍になる。"
  },
  {
    "名前": "シェルアーマー",
    "威力補正": "",
    "攻撃補正": "",
    "はりきり補正": "",
    "おやこあい補正": "",
    "防御補正": "",
    "その他の補正": "",
    "Mhalf": "",
    "Mfilter": "",
    "効果": "相手の攻撃が急所に当たらない。"
  },
  {
    "名前": "じきゅうりょく",
    "威力補正": "",
    "攻撃補正": "",
    "はりきり補正": "",
    "おやこあい補正": "",
    "防御補正": "",
    "その他の補正": "",
    "Mhalf": "",
    "Mfilter": "",
    "効果": "攻撃技を受けるとぼうぎょが1段階上がる。"
  },
  {
    "名前": "じしんかじょう",
    "威力補正": "",
    "攻撃補正": "",
    "はりきり補正": "",
    "おやこあい補正": "",
    "防御補正": "",
    "その他の補正": "",
    "Mhalf": "",
    "Mfilter": "",
    "効果": "ポケモンを倒すとこうげきが1段階上がる。"
  },
  {
    "名前": "しぜんかいふく",
    "威力補正": "",
    "攻撃補正": "",
    "はりきり補正": "",
    "おやこあい補正": "",
    "防御補正": "",
    "その他の補正": "",
    "Mhalf": "",
    "Mfilter": "",
    "効果": "手持ちに戻ると状態異常が回復する。"
  },
  {
    "名前": "しめりけ",
    "威力補正": "",
    "攻撃補正": "",
    "はりきり補正": "",
    "おやこあい補正": "",
    "防御補正": "",
    "その他の補正": "",
    "Mhalf": "",
    "Mfilter": "",
    "効果": "じばく、だいばくはつ、ビックリヘッド、ミストバースト、ゆうばくが使えなくなる。"
  },
  {
    "名前": "しゅうかく",
    "威力補正": "",
    "攻撃補正": "",
    "はりきり補正": "",
    "おやこあい補正": "",
    "防御補正": "",
    "その他の補正": "",
    "Mhalf": "",
    "Mfilter": "",
    "効果": "消費したきのみを復活させることがある。"
  },
  {
    "名前": "じゅうなん",
    "威力補正": "",
    "攻撃補正": "",
    "はりきり補正": "",
    "おやこあい補正": "",
    "防御補正": "",
    "その他の補正": "",
    "Mhalf": "",
    "Mfilter": "",
    "効果": "まひ状態にならない。"
  },
  {
    "名前": "じゅくせい",
    "威力補正": "",
    "攻撃補正": "",
    "はりきり補正": "",
    "おやこあい補正": "",
    "防御補正": "",
    "その他の補正": "",
    "Mhalf": "",
    "Mfilter": "",
    "効果": "きのみの効果が2倍になる。"
  },
  {
    "名前": "じょうききかん",
    "威力補正": "",
    "攻撃補正": "",
    "はりきり補正": "",
    "おやこあい補正": "",
    "防御補正": "",
    "その他の補正": "",
    "Mhalf": "",
    "Mfilter": "",
    "効果": "みずタイプかほのおタイプのわざを受けるとすばやさが6段階上がる。タマゴの孵化に必要な歩数が半減する。"
  },
  {
    "名前": "しょうりのほし",
    "威力補正": "",
    "攻撃補正": "",
    "はりきり補正": "",
    "おやこあい補正": "",
    "防御補正": "",
    "その他の補正": "",
    "Mhalf": "",
    "Mfilter": "",
    "効果": "自分と味方の命中率が1.1倍になる。"
  },
  {
    "名前": "じょおうのいげん",
    "威力補正": "",
    "攻撃補正": "",
    "はりきり補正": "",
    "おやこあい補正": "",
    "防御補正": "",
    "その他の補正": "",
    "Mhalf": "",
    "Mfilter": "",
    "効果": "自分と味方は相手側からの先制技を受けなくなる。"
  },
  {
    "名前": "じりょく",
    "威力補正": "",
    "攻撃補正": "",
    "はりきり補正": "",
    "おやこあい補正": "",
    "防御補正": "",
    "その他の補正": "",
    "Mhalf": "",
    "Mfilter": "",
    "効果": "はがねタイプのポケモンを逃げられなくする。"
  },
  {
    "名前": "しれいとう",
    "威力補正": "",
    "攻撃補正": "",
    "はりきり補正": "",
    "おやこあい補正": "",
    "防御補正": "",
    "その他の補正": "",
    "Mhalf": "",
    "Mfilter": "",
    "効果": "味方にヘイラッシャがいる場合その中に入り、全能力を2段階ずつ上げる。"
  },
  {
    "名前": "しろいけむり",
    "威力補正": "",
    "攻撃補正": "",
    "はりきり補正": "",
    "おやこあい補正": "",
    "防御補正": "",
    "その他の補正": "",
    "Mhalf": "",
    "Mfilter": "",
    "効果": "相手からランク補正を下げられない。"
  },
  {
    "名前": "しろのいななき",
    "威力補正": "",
    "攻撃補正": "",
    "はりきり補正": "",
    "おやこあい補正": "",
    "防御補正": "",
    "その他の補正": "",
    "Mhalf": "",
    "Mfilter": "",
    "効果": "ポケモンを倒すとこうげきが1段階上がる。"
  },
  {
    "名前": "しんがん",
    "威力補正": "",
    "攻撃補正": "",
    "はりきり補正": "",
    "おやこあい補正": "",
    "防御補正": "",
    "その他の補正": "",
    "Mhalf": "",
    "Mfilter": "",
    "効果": "ゴーストタイプにノーマル・かくとうわざが当たるようになる。命中率を下げられず、相手の回避率を無視できる。"
  },
  {
    "名前": "シンクロ",
    "威力補正": "",
    "攻撃補正": "",
    "はりきり補正": "",
    "おやこあい補正": "",
    "防御補正": "",
    "その他の補正": "",
    "Mhalf": "",
    "Mfilter": "",
    "効果": "どく・もうどく・まひ・やけど状態になったとき、相手も同じ状態異常にする。"
  },
  {
    "名前": "じんばいったい",
    "威力補正": "",
    "攻撃補正": "",
    "はりきり補正": "",
    "おやこあい補正": "",
    "防御補正": "",
    "その他の補正": "",
    "Mhalf": "",
    "Mfilter": "",
    "効果": "きんちょうかんとしろのいななきの効果をあわせ持つ。"
  },
  {
    "名前": "じんばいったい",
    "威力補正": "",
    "攻撃補正": "",
    "はりきり補正": "",
    "おやこあい補正": "",
    "防御補正": "",
    "その他の補正": "",
    "Mhalf": "",
    "Mfilter": "",
    "効果": "きんちょうかんとくろのいななきの効果をあわせ持つ。"
  },
  {
    "名前": "しんりょく",
    "威力補正": "",
    "攻撃補正": "攻撃補正",
    "はりきり補正": "",
    "おやこあい補正": "",
    "防御補正": "",
    "その他の補正": "",
    "Mhalf": "",
    "Mfilter": "",
    "効果": "HPが1/3以下になると、くさタイプのわざで攻撃するときのこうげき・とくこうが1.5倍になる。"
  },
  {
    "名前": "スイートベール",
    "威力補正": "",
    "攻撃補正": "",
    "はりきり補正": "",
    "おやこあい補正": "",
    "防御補正": "",
    "その他の補正": "",
    "Mhalf": "",
    "Mfilter": "",
    "効果": "自分と味方がねむり状態にならなくなる。"
  },
  {
    "名前": "すいすい",
    "威力補正": "",
    "攻撃補正": "",
    "はりきり補正": "",
    "おやこあい補正": "",
    "防御補正": "",
    "その他の補正": "",
    "Mhalf": "",
    "Mfilter": "",
    "効果": "あめのとき、すばやさが2倍になる。"
  },
  {
    "名前": "すいほう",
    "威力補正": "",
    "攻撃補正": "攻撃補正",
    "はりきり補正": "",
    "おやこあい補正": "",
    "防御補正": "",
    "その他の補正": "",
    "Mhalf": "",
    "Mfilter": "",
    "効果": "ほのおタイプのわざを受けるとき、相手のこうげき・とくこうを半分にする。やけど状態にならない。みずタイプのわざで攻撃するとき、こうげき・とくこうが2倍になる。"
  },
  {
    "名前": "スカイスキン",
    "威力補正": "威力補正",
    "攻撃補正": "",
    "はりきり補正": "",
    "おやこあい補正": "",
    "防御補正": "",
    "その他の補正": "",
    "Mhalf": "",
    "Mfilter": "",
    "効果": "ノーマルタイプのわざがひこうタイプになり、威力が1.2倍になる。"
  },
  {
    "名前": "スキルリンク",
    "威力補正": "",
    "攻撃補正": "",
    "はりきり補正": "",
    "おやこあい補正": "",
    "防御補正": "",
    "その他の補正": "",
    "Mhalf": "",
    "Mfilter": "",
    "効果": "連続攻撃技を常に最大回数出せる。"
  },
  {
    "名前": "スクリューおびれ",
    "威力補正": "",
    "攻撃補正": "",
    "はりきり補正": "",
    "おやこあい補正": "",
    "防御補正": "",
    "その他の補正": "",
    "Mhalf": "",
    "Mfilter": "",
    "効果": "攻撃を引き寄せる技や特性の効果を無視する。"
  },
  {
    "名前": "すじがねいり",
    "威力補正": "",
    "攻撃補正": "",
    "はりきり補正": "",
    "おやこあい補正": "",
    "防御補正": "",
    "その他の補正": "",
    "Mhalf": "",
    "Mfilter": "",
    "効果": "攻撃を引き寄せる技や特性の効果を無視する。"
  },
  {
    "名前": "すてみ",
    "威力補正": "威力補正",
    "攻撃補正": "",
    "はりきり補正": "",
    "おやこあい補正": "",
    "防御補正": "",
    "その他の補正": "",
    "Mhalf": "",
    "Mfilter": "",
    "効果": "反動を受けるわざなどの威力が1.2倍になる。"
  },
  {
    "名前": "スナイパー",
    "威力補正": "",
    "攻撃補正": "",
    "はりきり補正": "",
    "おやこあい補正": "",
    "防御補正": "",
    "その他の補正": "スナイパー補正",
    "Mhalf": "",
    "Mfilter": "",
    "効果": "急所に当てたときのダメージが2.25倍になる。"
  },
  {
    "名前": "すなおこし",
    "威力補正": "",
    "攻撃補正": "",
    "はりきり補正": "",
    "おやこあい補正": "",
    "防御補正": "",
    "その他の補正": "",
    "Mhalf": "",
    "Mfilter": "",
    "効果": "場に出たとき、すなあらしにする。"
  },
  {
    "名前": "すなかき",
    "威力補正": "",
    "攻撃補正": "",
    "はりきり補正": "",
    "おやこあい補正": "",
    "防御補正": "",
    "その他の補正": "",
    "Mhalf": "",
    "Mfilter": "",
    "効果": "すなあらしのとき、すばやさが2倍になる。"
  },
  {
    "名前": "すながくれ",
    "威力補正": "",
    "攻撃補正": "",
    "はりきり補正": "",
    "おやこあい補正": "",
    "防御補正": "",
    "その他の補正": "",
    "Mhalf": "",
    "Mfilter": "",
    "効果": "すなあらし状態なら回避率が1.25倍になる。"
  },
  {
    "名前": "すなのちから",
    "威力補正": "威力補正",
    "攻撃補正": "",
    "はりきり補正": "",
    "おやこあい補正": "",
    "防御補正": "",
    "その他の補正": "",
    "Mhalf": "",
    "Mfilter": "",
    "効果": "すなあらしのとき、いわ・じめん・はがねの威力が1.3倍になる。"
  },
  {
    "名前": "すなはき",
    "威力補正": "",
    "攻撃補正": "",
    "はりきり補正": "",
    "おやこあい補正": "",
    "防御補正": "",
    "その他の補正": "",
    "Mhalf": "",
    "Mfilter": "",
    "効果": "攻撃を受けると場をすなあらし状態にする。"
  },
  {
    "名前": "すりぬけ",
    "威力補正": "",
    "攻撃補正": "",
    "はりきり補正": "",
    "おやこあい補正": "",
    "防御補正": "",
    "その他の補正": "",
    "Mhalf": "",
    "Mfilter": "",
    "効果": "壁系のわざやみがわりを無視して攻撃できる。"
  },
  {
    "名前": "するどいめ",
    "威力補正": "",
    "攻撃補正": "",
    "はりきり補正": "",
    "おやこあい補正": "",
    "防御補正": "",
    "その他の補正": "",
    "Mhalf": "",
    "Mfilter": "",
    "効果": "命中率を下げられず、相手の回避率を無視できる。"
  },
  {
    "名前": "スロースタート",
    "威力補正": "",
    "攻撃補正": "攻撃補正",
    "はりきり補正": "",
    "おやこあい補正": "",
    "防御補正": "",
    "その他の補正": "",
    "Mhalf": "",
    "Mfilter": "",
    "効果": "5ターンの間こうげきとすばやさが半分になる。"
  },
  {
    "名前": "スワームチェンジ",
    "威力補正": "",
    "攻撃補正": "",
    "はりきり補正": "",
    "おやこあい補正": "",
    "防御補正": "",
    "その他の補正": "",
    "Mhalf": "",
    "Mfilter": "",
    "効果": "HPが半分以下になるとパーフェクトフォルムにフォルムチェンジする。"
  },
  {
    "名前": "せいぎのこころ",
    "威力補正": "",
    "攻撃補正": "",
    "はりきり補正": "",
    "おやこあい補正": "",
    "防御補正": "",
    "その他の補正": "",
    "Mhalf": "",
    "Mfilter": "",
    "効果": "あくタイプの攻撃を受けるとこうげきが1段階上がる。"
  },
  {
    "名前": "せいしんりょく",
    "威力補正": "",
    "攻撃補正": "",
    "はりきり補正": "",
    "おやこあい補正": "",
    "防御補正": "",
    "その他の補正": "",
    "Mhalf": "",
    "Mfilter": "",
    "効果": "ひるみ状態にならない。"
  },
  {
    "名前": "せいでんき",
    "威力補正": "",
    "攻撃補正": "",
    "はりきり補正": "",
    "おやこあい補正": "",
    "防御補正": "",
    "その他の補正": "",
    "Mhalf": "",
    "Mfilter": "",
    "効果": "直接攻撃を受けたとき、相手をまひ状態にすることがある。"
  },
  {
    "名前": "ぜったいねむり",
    "威力補正": "",
    "攻撃補正": "",
    "はりきり補正": "",
    "おやこあい補正": "",
    "防御補正": "",
    "その他の補正": "",
    "Mhalf": "",
    "Mfilter": "",
    "効果": "状態異常にならない。ねむり状態のように扱われる。"
  },
  {
    "名前": "ゼロフォーミング",
    "威力補正": "",
    "攻撃補正": "",
    "はりきり補正": "",
    "おやこあい補正": "",
    "防御補正": "",
    "その他の補正": "",
    "Mhalf": "",
    "Mfilter": "",
    "効果": "テラパゴスがステラタイプにテラスタルしたとき、場の天候とフィールドを消滅させる。"
  },
  {
    "名前": "そうしょく",
    "威力補正": "",
    "攻撃補正": "",
    "はりきり補正": "",
    "おやこあい補正": "",
    "防御補正": "",
    "その他の補正": "くさ無効",
    "Mhalf": "",
    "Mfilter": "",
    "効果": "くさタイプのわざを無効化し、こうげきが1段階上がる。"
  },
  {
    "名前": "そうだいしょう",
    "威力補正": "威力補正",
    "攻撃補正": "",
    "はりきり補正": "",
    "おやこあい補正": "",
    "防御補正": "",
    "その他の補正": "",
    "Mhalf": "",
    "Mfilter": "",
    "効果": "場に出たときに、ひんしになった味方1体につき10%ずつ攻撃技の威力が上がる。"
  },
  {
    "名前": "ソウルハート",
    "威力補正": "",
    "攻撃補正": "",
    "はりきり補正": "",
    "おやこあい補正": "",
    "防御補正": "",
    "その他の補正": "",
    "Mhalf": "",
    "Mfilter": "",
    "効果": "場のポケモンがひんしになるととくこうが1段階上がる。"
  },
  {
    "名前": "ダークオーラ",
    "威力補正": "威力補正",
    "攻撃補正": "",
    "はりきり補正": "",
    "おやこあい補正": "",
    "防御補正": "",
    "その他の補正": "",
    "Mhalf": "",
    "Mfilter": "",
    "効果": "場にいるポケモンのあくわざの威力が1.33倍になる。"
  },
  {
    "名前": "ターボブレイズ",
    "威力補正": "",
    "攻撃補正": "",
    "はりきり補正": "",
    "おやこあい補正": "",
    "防御補正": "",
    "その他の補正": "",
    "Mhalf": "",
    "Mfilter": "",
    "効果": "特性の影響を受けずに技を出せる。"
  },
  {
    "名前": "たいねつ",
    "威力補正": "",
    "攻撃補正": "攻撃補正",
    "はりきり補正": "",
    "おやこあい補正": "",
    "防御補正": "",
    "その他の補正": "",
    "Mhalf": "",
    "Mfilter": "",
    "効果": "ほのおわざを受けた時に威力を半減する。やけど状態のダメージを半減する。"
  },
  {
    "名前": "ダウンロード",
    "威力補正": "",
    "攻撃補正": "",
    "はりきり補正": "",
    "おやこあい補正": "",
    "防御補正": "",
    "その他の補正": "",
    "Mhalf": "",
    "Mfilter": "",
    "効果": "相手のステータスに応じてこうげきかとくこうが1段階上がる。"
  },
  {
    "名前": "だっぴ",
    "威力補正": "",
    "攻撃補正": "",
    "はりきり補正": "",
    "おやこあい補正": "",
    "防御補正": "",
    "その他の補正": "",
    "Mhalf": "",
    "Mfilter": "",
    "効果": "状態異常を治すことがある。"
  },
  {
    "名前": "たまひろい",
    "威力補正": "",
    "攻撃補正": "",
    "はりきり補正": "",
    "おやこあい補正": "",
    "防御補正": "",
    "その他の補正": "",
    "Mhalf": "",
    "Mfilter": "",
    "効果": "野生ポケモンの捕獲に失敗した際、ボールを拾ってくる。"
  },
  {
    "名前": "ダルマモード",
    "威力補正": "",
    "攻撃補正": "",
    "はりきり補正": "",
    "おやこあい補正": "",
    "防御補正": "",
    "その他の補正": "",
    "Mhalf": "",
    "Mfilter": "",
    "効果": "HPが半分以下になるとヒヒダルマのフォルムが変化する。"
  },
  {
    "名前": "たんじゅん",
    "威力補正": "",
    "攻撃補正": "",
    "はりきり補正": "",
    "おやこあい補正": "",
    "防御補正": "",
    "その他の補正": "",
    "Mhalf": "",
    "Mfilter": "",
    "効果": "ランク補正の変化量が2倍になる。"
  },
  {
    "名前": "ちからずく",
    "威力補正": "威力補正",
    "攻撃補正": "",
    "はりきり補正": "",
    "おやこあい補正": "",
    "防御補正": "",
    "その他の補正": "",
    "Mhalf": "",
    "Mfilter": "",
    "効果": "わざの追加効果が出なくなり、そのわざの威力が1.3倍に上がる。"
  },
  {
    "名前": "ちからもち",
    "威力補正": "",
    "攻撃補正": "攻撃補正",
    "はりきり補正": "",
    "おやこあい補正": "",
    "防御補正": "",
    "その他の補正": "",
    "Mhalf": "",
    "Mfilter": "",
    "効果": "こうげきが2倍になる。"
  },
  {
    "名前": "ちくでん",
    "威力補正": "",
    "攻撃補正": "",
    "はりきり補正": "",
    "おやこあい補正": "",
    "防御補正": "",
    "その他の補正": "でんき無効",
    "Mhalf": "",
    "Mfilter": "",
    "効果": "でんきタイプのわざを無効化しHPを1/4回復する。"
  },
  {
    "名前": "ちどりあし",
    "威力補正": "",
    "攻撃補正": "",
    "はりきり補正": "",
    "おやこあい補正": "",
    "防御補正": "",
    "その他の補正": "",
    "Mhalf": "",
    "Mfilter": "",
    "効果": "こんらん状態のとき、回避率が2倍になる。"
  },
  {
    "名前": "ちょすい",
    "威力補正": "",
    "攻撃補正": "",
    "はりきり補正": "",
    "おやこあい補正": "",
    "防御補正": "",
    "その他の補正": "みず無効",
    "Mhalf": "",
    "Mfilter": "",
    "効果": "みずタイプのわざを無効化しHPを1/4回復する。"
  },
  {
    "名前": "テイルアーマー",
    "威力補正": "",
    "攻撃補正": "",
    "はりきり補正": "",
    "おやこあい補正": "",
    "防御補正": "",
    "その他の補正": "",
    "Mhalf": "",
    "Mfilter": "",
    "効果": "自分と味方は相手側からの先制技を受けなくなる。"
  },
  {
    "名前": "てきおうりょく",
    "威力補正": "",
    "攻撃補正": "",
    "はりきり補正": "",
    "おやこあい補正": "",
    "防御補正": "",
    "その他の補正": "",
    "Mhalf": "",
    "Mfilter": "",
    "効果": "タイプ一致のダメージ補正が1.5倍から2倍になる。"
  },
  {
    "名前": "テクニシャン",
    "威力補正": "威力補正",
    "攻撃補正": "",
    "はりきり補正": "",
    "おやこあい補正": "",
    "防御補正": "",
    "その他の補正": "",
    "Mhalf": "",
    "Mfilter": "",
    "効果": "威力が低いわざの威力が1.5倍になる。"
  },
  {
    "名前": "てつのこぶし",
    "威力補正": "威力補正",
    "攻撃補正": "",
    "はりきり補正": "",
    "おやこあい補正": "",
    "防御補正": "",
    "その他の補正": "",
    "Mhalf": "",
    "Mfilter": "",
    "効果": "パンチわざの威力が1.2倍になる。"
  },
  {
    "名前": "てつのトゲ",
    "威力補正": "",
    "攻撃補正": "",
    "はりきり補正": "",
    "おやこあい補正": "",
    "防御補正": "",
    "その他の補正": "",
    "Mhalf": "",
    "Mfilter": "",
    "効果": "直接攻撃を受けたとき、相手に最大HPの1/8分のダメージを与える。"
  },
  {
    "名前": "テラスシェル",
    "威力補正": "",
    "攻撃補正": "",
    "はりきり補正": "",
    "おやこあい補正": "",
    "防御補正": "",
    "その他の補正": "",
    "Mhalf": "",
    "Mfilter": "",
    "効果": "HPが満タンならば受ける攻撃技の相性が全て今ひとつになる。"
  },
  {
    "名前": "テラスチェンジ",
    "威力補正": "",
    "攻撃補正": "",
    "はりきり補正": "",
    "おやこあい補正": "",
    "防御補正": "",
    "その他の補正": "",
    "Mhalf": "",
    "Mfilter": "",
    "効果": "場に出たとき、テラパゴスがテラスタルフォルムにフォルムチェンジする。"
  },
  {
    "名前": "テラボルテージ",
    "威力補正": "",
    "攻撃補正": "",
    "はりきり補正": "",
    "おやこあい補正": "",
    "防御補正": "",
    "その他の補正": "",
    "Mhalf": "",
    "Mfilter": "",
    "効果": "特性の影響を受けずに技を出せる。"
  },
  {
    "名前": "デルタストリーム",
    "威力補正": "",
    "攻撃補正": "",
    "はりきり補正": "",
    "おやこあい補正": "",
    "防御補正": "",
    "その他の補正": "",
    "Mhalf": "",
    "Mfilter": "",
    "効果": "天気をらんきりゅうにする。"
  },
  {
    "名前": "テレパシー",
    "威力補正": "",
    "攻撃補正": "",
    "はりきり補正": "",
    "おやこあい補正": "",
    "防御補正": "",
    "その他の補正": "",
    "Mhalf": "",
    "Mfilter": "",
    "効果": "味方からの攻撃を無効化する。"
  },
  {
    "名前": "でんきエンジン",
    "威力補正": "",
    "攻撃補正": "",
    "はりきり補正": "",
    "おやこあい補正": "",
    "防御補正": "",
    "その他の補正": "でんき無効",
    "Mhalf": "",
    "Mfilter": "",
    "効果": "でんきタイプのわざを無効化して、すばやさが1段階上がる。"
  },
  {
    "名前": "でんきにかえる",
    "威力補正": "",
    "攻撃補正": "",
    "はりきり補正": "",
    "おやこあい補正": "",
    "防御補正": "",
    "その他の補正": "",
    "Mhalf": "",
    "Mfilter": "",
    "効果": "攻撃技を受けるとじゅうでん状態になる。"
  },
  {
    "名前": "てんきや",
    "威力補正": "",
    "攻撃補正": "",
    "はりきり補正": "",
    "おやこあい補正": "",
    "防御補正": "",
    "その他の補正": "",
    "Mhalf": "",
    "Mfilter": "",
    "効果": "場の天気によってタイプ・フォルムが変化する。"
  },
  {
    "名前": "てんねん",
    "威力補正": "",
    "攻撃補正": "",
    "はりきり補正": "",
    "おやこあい補正": "",
    "防御補正": "",
    "その他の補正": "",
    "Mhalf": "",
    "Mfilter": "",
    "効果": "相手のランク補正を無視する。"
  },
  {
    "名前": "てんのめぐみ",
    "威力補正": "",
    "攻撃補正": "",
    "はりきり補正": "",
    "おやこあい補正": "",
    "防御補正": "",
    "その他の補正": "",
    "Mhalf": "",
    "Mfilter": "",
    "効果": "追加効果の出る確率が2倍になる。"
  },
  {
    "名前": "とうそうしん",
    "威力補正": "威力補正",
    "攻撃補正": "",
    "はりきり補正": "",
    "おやこあい補正": "",
    "防御補正": "",
    "その他の補正": "",
    "Mhalf": "",
    "Mfilter": "",
    "効果": "相手が同性のときはわざの威力が1.25倍になり、異性のときは0.75倍になる。"
  },
  {
    "名前": "どくくぐつ",
    "威力補正": "",
    "攻撃補正": "",
    "はりきり補正": "",
    "おやこあい補正": "",
    "防御補正": "",
    "その他の補正": "",
    "Mhalf": "",
    "Mfilter": "",
    "効果": "使用した技でどく・もうどく状態になったポケモンは、こんらん状態にもなる。"
  },
  {
    "名前": "どくげしょう",
    "威力補正": "",
    "攻撃補正": "",
    "はりきり補正": "",
    "おやこあい補正": "",
    "防御補正": "",
    "その他の補正": "",
    "Mhalf": "",
    "Mfilter": "",
    "効果": "物理技を受けたとき、相手の場をどくびし状態にする。"
  },
  {
    "名前": "どくしゅ",
    "威力補正": "",
    "攻撃補正": "",
    "はりきり補正": "",
    "おやこあい補正": "",
    "防御補正": "",
    "その他の補正": "",
    "Mhalf": "",
    "Mfilter": "",
    "効果": "直接攻撃を使ったとき、相手をどく状態にすることがある。"
  },
  {
    "名前": "どくのくさり",
    "威力補正": "",
    "攻撃補正": "",
    "はりきり補正": "",
    "おやこあい補正": "",
    "防御補正": "",
    "その他の補正": "",
    "Mhalf": "",
    "Mfilter": "",
    "効果": "攻撃技を使ったとき、相手をもうどく状態にすることがある。"
  },
  {
    "名前": "どくのトゲ",
    "威力補正": "",
    "攻撃補正": "",
    "はりきり補正": "",
    "おやこあい補正": "",
    "防御補正": "",
    "その他の補正": "",
    "Mhalf": "",
    "Mfilter": "",
    "効果": "直接攻撃を受けたとき、相手をどく状態にすることがある。"
  },
  {
    "名前": "どくぼうそう",
    "威力補正": "威力補正",
    "攻撃補正": "",
    "はりきり補正": "",
    "おやこあい補正": "",
    "防御補正": "",
    "その他の補正": "",
    "Mhalf": "",
    "Mfilter": "",
    "効果": "どく・もうどく状態のとき、物理技の威力が1.5倍になる。"
  },
  {
    "名前": "どしょく",
    "威力補正": "",
    "攻撃補正": "",
    "はりきり補正": "",
    "おやこあい補正": "",
    "防御補正": "",
    "その他の補正": "じめん無効",
    "Mhalf": "",
    "Mfilter": "",
    "効果": "じめんタイプの技を無効化し、最大HPの1/4を回復する。"
  },
  {
    "名前": "とびだすなかみ",
    "威力補正": "",
    "攻撃補正": "",
    "はりきり補正": "",
    "おやこあい補正": "",
    "防御補正": "",
    "その他の補正": "",
    "Mhalf": "",
    "Mfilter": "",
    "効果": "ひんしになったとき、直前のHP分だけ相手にダメージを与える。"
  },
  {
    "名前": "トランジスタ",
    "威力補正": "",
    "攻撃補正": "攻撃補正",
    "はりきり補正": "",
    "おやこあい補正": "",
    "防御補正": "",
    "その他の補正": "",
    "Mhalf": "",
    "Mfilter": "",
    "効果": "でんきタイプのわざで攻撃するとき、こうげき・とくこうが1.3倍になる。"
  },
  {
    "名前": "トレース",
    "威力補正": "",
    "攻撃補正": "",
    "はりきり補正": "",
    "おやこあい補正": "",
    "防御補正": "",
    "その他の補正": "",
    "Mhalf": "",
    "Mfilter": "",
    "効果": "場に出たとき、相手と同じ特性になる。"
  },
  {
    "名前": "とれないにおい",
    "威力補正": "",
    "攻撃補正": "",
    "はりきり補正": "",
    "おやこあい補正": "",
    "防御補正": "",
    "その他の補正": "",
    "Mhalf": "",
    "Mfilter": "",
    "効果": "直接攻撃を受けたとき、相手の特性もとれないにおいにする。"
  },
  {
    "名前": "どんかん",
    "威力補正": "",
    "攻撃補正": "",
    "はりきり補正": "",
    "おやこあい補正": "",
    "防御補正": "",
    "その他の補正": "",
    "Mhalf": "",
    "Mfilter": "",
    "効果": "メロメロ状態・ちょうはつ状態にならない。ゆうわくを無効化する。"
  },
  {
    "名前": "ナイトメア",
    "威力補正": "",
    "攻撃補正": "",
    "はりきり補正": "",
    "おやこあい補正": "",
    "防御補正": "",
    "その他の補正": "",
    "Mhalf": "",
    "Mfilter": "",
    "効果": "ねむり状態のポケモンのHPを1/8減らす。"
  },
  {
    "名前": "なまけ",
    "威力補正": "",
    "攻撃補正": "",
    "はりきり補正": "",
    "おやこあい補正": "",
    "防御補正": "",
    "その他の補正": "",
    "Mhalf": "",
    "Mfilter": "",
    "効果": "2ターンに1回しか行動できない。"
  },
  {
    "名前": "にげあし",
    "威力補正": "",
    "攻撃補正": "",
    "はりきり補正": "",
    "おやこあい補正": "",
    "防御補正": "",
    "その他の補正": "",
    "Mhalf": "",
    "Mfilter": "",
    "効果": "野生ポケモンから必ず逃げられる。"
  },
  {
    "名前": "にげごし",
    "威力補正": "",
    "攻撃補正": "",
    "はりきり補正": "",
    "おやこあい補正": "",
    "防御補正": "",
    "その他の補正": "",
    "Mhalf": "",
    "Mfilter": "",
    "効果": "HPが半分以下になると交代する。"
  },
  {
    "名前": "ぬめぬめ",
    "威力補正": "",
    "攻撃補正": "",
    "はりきり補正": "",
    "おやこあい補正": "",
    "防御補正": "",
    "その他の補正": "",
    "Mhalf": "",
    "Mfilter": "",
    "効果": "直接攻撃を受けたとき、相手のすばやさを1段階下げる。"
  },
  {
    "名前": "ねつこうかん",
    "威力補正": "",
    "攻撃補正": "",
    "はりきり補正": "",
    "おやこあい補正": "",
    "防御補正": "",
    "その他の補正": "",
    "Mhalf": "",
    "Mfilter": "",
    "効果": "ほのおタイプの攻撃を受けるとこうげきが1段階上がる。やけど状態にならない。"
  },
  {
    "名前": "ねつぼうそう",
    "威力補正": "威力補正",
    "攻撃補正": "",
    "はりきり補正": "",
    "おやこあい補正": "",
    "防御補正": "",
    "その他の補正": "",
    "Mhalf": "",
    "Mfilter": "",
    "効果": "やけど状態のとき、特殊技の威力が1.5倍になる。"
  },
  {
    "名前": "ねんちゃく",
    "威力補正": "",
    "攻撃補正": "",
    "はりきり補正": "",
    "おやこあい補正": "",
    "防御補正": "",
    "その他の補正": "",
    "Mhalf": "",
    "Mfilter": "",
    "効果": "持ち物を奪われない。"
  },
  {
    "名前": "ノーガード",
    "威力補正": "",
    "攻撃補正": "",
    "はりきり補正": "",
    "おやこあい補正": "",
    "防御補正": "",
    "その他の補正": "",
    "Mhalf": "",
    "Mfilter": "",
    "効果": "自分と相手のわざが必中になる。"
  },
  {
    "名前": "ノーてんき",
    "威力補正": "",
    "攻撃補正": "",
    "はりきり補正": "",
    "おやこあい補正": "",
    "防御補正": "",
    "その他の補正": "",
    "Mhalf": "",
    "Mfilter": "",
    "効果": "天気の影響が無くなる。"
  },
  {
    "名前": "ノーマルスキン",
    "威力補正": "威力補正",
    "攻撃補正": "",
    "はりきり補正": "",
    "おやこあい補正": "",
    "防御補正": "",
    "その他の補正": "",
    "Mhalf": "",
    "Mfilter": "",
    "効果": "全てのわざがノーマルタイプとなり、タイプを変えた技の威力が1.2倍になる。"
  },
  {
    "名前": "のろわれボディ",
    "威力補正": "",
    "攻撃補正": "",
    "はりきり補正": "",
    "おやこあい補正": "",
    "防御補正": "",
    "その他の補正": "",
    "Mhalf": "",
    "Mfilter": "",
    "効果": "攻撃技を受けると相手をかなしばりにすることがある。"
  },
  {
    "名前": "ハードロック",
    "威力補正": "",
    "攻撃補正": "",
    "はりきり補正": "",
    "おやこあい補正": "",
    "防御補正": "",
    "その他の補正": "",
    "Mhalf": "",
    "Mfilter": "Mfilter",
    "効果": "受ける効果抜群のわざのダメージが0.75倍になる。"
  },
  {
    "名前": "はがねつかい",
    "威力補正": "",
    "攻撃補正": "攻撃補正",
    "はりきり補正": "",
    "おやこあい補正": "",
    "防御補正": "",
    "その他の補正": "",
    "Mhalf": "",
    "Mfilter": "",
    "効果": "はがねタイプのわざで攻撃するとき、こうげき・とくこうが1.5倍になる。"
  },
  {
    "名前": "はがねのせいしん",
    "威力補正": "威力補正",
    "攻撃補正": "",
    "はりきり補正": "",
    "おやこあい補正": "",
    "防御補正": "",
    "その他の補正": "",
    "Mhalf": "",
    "Mfilter": "",
    "効果": "自分・味方のはがねタイプの技の威力が1.5倍になる。"
  },
  {
    "名前": "ばけのかわ",
    "威力補正": "",
    "攻撃補正": "",
    "はりきり補正": "",
    "おやこあい補正": "",
    "防御補正": "",
    "その他の補正": "",
    "Mhalf": "",
    "Mfilter": "",
    "効果": "1回だけ攻撃技のダメージを無効化する。発動すると最大HPの1/8が減少する。"
  },
  {
    "名前": "はじまりのうみ",
    "威力補正": "",
    "攻撃補正": "",
    "はりきり補正": "",
    "おやこあい補正": "",
    "防御補正": "",
    "その他の補正": "",
    "Mhalf": "",
    "Mfilter": "",
    "効果": "天気をおおあめにする。"
  },
  {
    "名前": "パステルベール",
    "威力補正": "",
    "攻撃補正": "",
    "はりきり補正": "",
    "おやこあい補正": "",
    "防御補正": "",
    "その他の補正": "",
    "Mhalf": "",
    "Mfilter": "",
    "効果": "自分と味方がどく状態にならない。"
  },
  {
    "名前": "はっこう",
    "威力補正": "",
    "攻撃補正": "",
    "はりきり補正": "",
    "おやこあい補正": "",
    "防御補正": "",
    "その他の補正": "",
    "Mhalf": "",
    "Mfilter": "",
    "効果": "命中率を下げられず、相手の回避率を無視できる。"
  },
  {
    "名前": "バッテリー",
    "威力補正": "威力補正",
    "攻撃補正": "",
    "はりきり補正": "",
    "おやこあい補正": "",
    "防御補正": "",
    "その他の補正": "",
    "Mhalf": "",
    "Mfilter": "",
    "効果": "味方の特殊技の威力が1.3倍になる。"
  },
  {
    "名前": "はとむね",
    "威力補正": "",
    "攻撃補正": "",
    "はりきり補正": "",
    "おやこあい補正": "",
    "防御補正": "",
    "その他の補正": "",
    "Mhalf": "",
    "Mfilter": "",
    "効果": "相手からぼうぎょを下げられない。"
  },
  {
    "名前": "バトルスイッチ",
    "威力補正": "",
    "攻撃補正": "",
    "はりきり補正": "",
    "おやこあい補正": "",
    "防御補正": "",
    "その他の補正": "",
    "Mhalf": "",
    "Mfilter": "",
    "効果": "使う技に応じてギルガルドのフォルムを変化させる。"
  },
  {
    "名前": "ハドロンエンジン",
    "威力補正": "",
    "攻撃補正": "攻撃補正",
    "はりきり補正": "",
    "おやこあい補正": "",
    "防御補正": "",
    "その他の補正": "",
    "Mhalf": "",
    "Mfilter": "",
    "効果": "場に出たとき、エレキフィールド状態にし、その間とくこうも4/3倍になる。"
  },
  {
    "名前": "はやあし",
    "威力補正": "",
    "攻撃補正": "",
    "はりきり補正": "",
    "おやこあい補正": "",
    "防御補正": "",
    "その他の補正": "",
    "Mhalf": "",
    "Mfilter": "",
    "効果": "状態異常のとき、すばやさが1.5倍になる。"
  },
  {
    "名前": "はやおき",
    "威力補正": "",
    "攻撃補正": "",
    "はりきり補正": "",
    "おやこあい補正": "",
    "防御補正": "",
    "その他の補正": "",
    "Mhalf": "",
    "Mfilter": "",
    "効果": "ねむりのターンの消費量が2倍になる。"
  },
  {
    "名前": "はやてのつばさ",
    "威力補正": "",
    "攻撃補正": "",
    "はりきり補正": "",
    "おやこあい補正": "",
    "防御補正": "",
    "その他の補正": "",
    "Mhalf": "",
    "Mfilter": "",
    "効果": "HPが満タンのとき、ひこうわざの優先度を1高くして出せる。"
  },
  {
    "名前": "はらぺこスイッチ",
    "威力補正": "",
    "攻撃補正": "",
    "はりきり補正": "",
    "おやこあい補正": "",
    "防御補正": "",
    "その他の補正": "",
    "Mhalf": "",
    "Mfilter": "",
    "効果": "1ターンごとにモルペコのフォルムが変わる。"
  },
  {
    "名前": "バリアフリー",
    "威力補正": "",
    "攻撃補正": "",
    "はりきり補正": "",
    "おやこあい補正": "",
    "防御補正": "",
    "その他の補正": "",
    "Mhalf": "",
    "Mfilter": "",
    "効果": "場に出たとき、お互いの壁を解除する。"
  },
  {
    "名前": "はりきり",
    "威力補正": "",
    "攻撃補正": "",
    "はりきり補正": "はりきり補正",
    "おやこあい補正": "",
    "防御補正": "",
    "その他の補正": "",
    "Mhalf": "",
    "Mfilter": "",
    "効果": "こうげきが1.5倍になるが、命中率が0.8倍になる。"
  },
  {
    "名前": "はりこみ",
    "威力補正": "",
    "攻撃補正": "攻撃補正",
    "はりきり補正": "",
    "おやこあい補正": "",
    "防御補正": "",
    "その他の補正": "",
    "Mhalf": "",
    "Mfilter": "",
    "効果": "交代して出てきたポケモンに攻撃するとき、こうげき・とくこうが2倍になる。"
  },
  {
    "名前": "パワースポット",
    "威力補正": "威力補正",
    "攻撃補正": "",
    "はりきり補正": "",
    "おやこあい補正": "",
    "防御補正": "",
    "その他の補正": "",
    "Mhalf": "",
    "Mfilter": "",
    "効果": "味方の攻撃技の威力が1.3倍になる。"
  },
  {
    "名前": "パンクロック",
    "威力補正": "威力補正",
    "攻撃補正": "",
    "はりきり補正": "",
    "おやこあい補正": "",
    "防御補正": "",
    "その他の補正": "",
    "Mhalf": "Mhalf",
    "Mfilter": "",
    "効果": "使用する音のわざの威力が1.3倍になる。受ける音のわざのダメージが半減する。"
  },
  {
    "名前": "ばんけん",
    "威力補正": "",
    "攻撃補正": "",
    "はりきり補正": "",
    "おやこあい補正": "",
    "防御補正": "",
    "その他の補正": "",
    "Mhalf": "",
    "Mfilter": "",
    "効果": "いかくを受けるとこうげきが1段階上がる。相手の交代させる技やレッドカードの効果を受けない。"
  },
  {
    "名前": "はんすう",
    "威力補正": "",
    "攻撃補正": "",
    "はりきり補正": "",
    "おやこあい補正": "",
    "防御補正": "",
    "その他の補正": "",
    "Mhalf": "",
    "Mfilter": "",
    "効果": "きのみを食べたとき、次のターンの終了時にまた同じきのみを食べる。"
  },
  {
    "名前": "ビーストブースト",
    "威力補正": "",
    "攻撃補正": "",
    "はりきり補正": "",
    "おやこあい補正": "",
    "防御補正": "",
    "その他の補正": "",
    "Mhalf": "",
    "Mfilter": "",
    "効果": "ポケモンを倒すと、自分の最も高い能力が1段階上がる。"
  },
  {
    "名前": "ヒーリングシフト",
    "威力補正": "",
    "攻撃補正": "",
    "はりきり補正": "",
    "おやこあい補正": "",
    "防御補正": "",
    "その他の補正": "",
    "Mhalf": "",
    "Mfilter": "",
    "効果": "HPを回復するわざの優先度を3高くして出せる。"
  },
  {
    "名前": "ひでり",
    "威力補正": "",
    "攻撃補正": "",
    "はりきり補正": "",
    "おやこあい補正": "",
    "防御補正": "",
    "その他の補正": "",
    "Mhalf": "",
    "Mfilter": "",
    "効果": "場の天気をにほんばれにする。"
  },
  {
    "名前": "ひとでなし",
    "威力補正": "",
    "攻撃補正": "",
    "はりきり補正": "",
    "おやこあい補正": "",
    "防御補正": "",
    "その他の補正": "",
    "Mhalf": "",
    "Mfilter": "",
    "効果": "相手がどく・もうどく状態のとき、自分のわざが急所に当たる。"
  },
  {
    "名前": "ひひいろのこどう",
    "威力補正": "",
    "攻撃補正": "攻撃補正",
    "はりきり補正": "",
    "おやこあい補正": "",
    "防御補正": "",
    "その他の補正": "",
    "Mhalf": "",
    "Mfilter": "",
    "効果": "場に出たとき、にほんばれ状態にし、その間こうげきも4/3倍になる。"
  },
  {
    "名前": "ビビッドボディ",
    "威力補正": "",
    "攻撃補正": "",
    "はりきり補正": "",
    "おやこあい補正": "",
    "防御補正": "",
    "その他の補正": "",
    "Mhalf": "",
    "Mfilter": "",
    "効果": "自分と味方は相手側からの先制技を受けなくなる。"
  },
  {
    "名前": "びびり",
    "威力補正": "",
    "攻撃補正": "",
    "はりきり補正": "",
    "おやこあい補正": "",
    "防御補正": "",
    "その他の補正": "",
    "Mhalf": "",
    "Mfilter": "",
    "効果": "ゴースト・むし・あくタイプの攻撃を受けるとすばやさが1段階上がる。"
  },
  {
    "名前": "ひらいしん",
    "威力補正": "",
    "攻撃補正": "",
    "はりきり補正": "",
    "おやこあい補正": "",
    "防御補正": "",
    "その他の補正": "でんき無効",
    "Mhalf": "",
    "Mfilter": "",
    "効果": "でんきわざの対象を自分にし、無効化してとくこうを1段階上げる。"
  },
  {
    "名前": "びんじょう",
    "威力補正": "",
    "攻撃補正": "",
    "はりきり補正": "",
    "おやこあい補正": "",
    "防御補正": "",
    "その他の補正": "",
    "Mhalf": "",
    "Mfilter": "",
    "効果": "相手のランク補正が上昇したとき、自分も同じだけランクを上げる。"
  },
  {
    "名前": "ファーコート",
    "威力補正": "",
    "攻撃補正": "",
    "はりきり補正": "",
    "おやこあい補正": "",
    "防御補正": "防御補正",
    "その他の補正": "",
    "Mhalf": "",
    "Mfilter": "",
    "効果": "ぼうぎょが2倍になる。"
  },
  {
    "名前": "ファントムガード",
    "威力補正": "",
    "攻撃補正": "",
    "はりきり補正": "",
    "おやこあい補正": "",
    "防御補正": "",
    "その他の補正": "",
    "Mhalf": "Mhalf",
    "Mfilter": "",
    "効果": "HPが満タンのとき、受けるダメージが半減する。"
  },
  {
    "名前": "フィルター",
    "威力補正": "",
    "攻撃補正": "",
    "はりきり補正": "",
    "おやこあい補正": "",
    "防御補正": "",
    "その他の補正": "",
    "Mhalf": "",
    "Mfilter": "Mfilter",
    "効果": "受ける効果抜群のわざのダメージが0.75倍になる。"
  },
  {
    "名前": "ふうりょくでんき",
    "威力補正": "",
    "攻撃補正": "",
    "はりきり補正": "",
    "おやこあい補正": "",
    "防御補正": "",
    "その他の補正": "",
    "Mhalf": "",
    "Mfilter": "",
    "効果": "場がおいかぜ状態に変わるか、風の技でダメージを受けるとじゅうでん状態になる。"
  },
  {
    "名前": "フェアリーオーラ",
    "威力補正": "威力補正",
    "攻撃補正": "",
    "はりきり補正": "",
    "おやこあい補正": "",
    "防御補正": "",
    "その他の補正": "",
    "Mhalf": "",
    "Mfilter": "",
    "効果": "場にいるポケモンのフェアリーわざの威力が1.33倍になる。"
  },
  {
    "名前": "フェアリースキン",
    "威力補正": "威力補正",
    "攻撃補正": "",
    "はりきり補正": "",
    "おやこあい補正": "",
    "防御補正": "",
    "その他の補正": "",
    "Mhalf": "",
    "Mfilter": "",
    "効果": "ノーマルタイプのわざがフェアリータイプになり、威力が1.2倍になる。"
  },
  {
    "名前": "ふかしのこぶし",
    "威力補正": "",
    "攻撃補正": "",
    "はりきり補正": "",
    "おやこあい補正": "",
    "防御補正": "",
    "その他の補正": "",
    "Mhalf": "",
    "Mfilter": "",
    "効果": "直接攻撃を使ったとき、相手のまもる状態を無視する。"
  },
  {
    "名前": "ぶきよう",
    "威力補正": "",
    "攻撃補正": "",
    "はりきり補正": "",
    "おやこあい補正": "",
    "防御補正": "",
    "その他の補正": "",
    "Mhalf": "",
    "Mfilter": "",
    "効果": "自分の持ち物の効果がなくなる。"
  },
  {
    "名前": "ふくがん",
    "威力補正": "",
    "攻撃補正": "",
    "はりきり補正": "",
    "おやこあい補正": "",
    "防御補正": "",
    "その他の補正": "",
    "Mhalf": "",
    "Mfilter": "",
    "効果": "使用する技の命中率が1.3倍に上がる。"
  },
  {
    "名前": "ふくつのこころ",
    "威力補正": "",
    "攻撃補正": "",
    "はりきり補正": "",
    "おやこあい補正": "",
    "防御補正": "",
    "その他の補正": "",
    "Mhalf": "",
    "Mfilter": "",
    "効果": "ひるむとすばやさが1段階上がる。"
  },
  {
    "名前": "ふくつのたて",
    "威力補正": "",
    "攻撃補正": "",
    "はりきり補正": "",
    "おやこあい補正": "",
    "防御補正": "",
    "その他の補正": "",
    "Mhalf": "",
    "Mfilter": "",
    "効果": "場に出たとき、ぼうぎょが1段階上がる。"
  },
  {
    "名前": "ふしぎなうろこ",
    "威力補正": "",
    "攻撃補正": "",
    "はりきり補正": "",
    "おやこあい補正": "",
    "防御補正": "防御補正",
    "その他の補正": "",
    "Mhalf": "",
    "Mfilter": "",
    "効果": "状態異常のとき、ぼうぎょが1.5倍になる。"
  },
  {
    "名前": "ふしぎなまもり",
    "威力補正": "",
    "攻撃補正": "",
    "はりきり補正": "",
    "おやこあい補正": "",
    "防御補正": "",
    "その他の補正": "",
    "Mhalf": "",
    "Mfilter": "",
    "効果": "効果抜群となるタイプ以外の攻撃技を無効化する。"
  },
  {
    "名前": "ふしょく",
    "威力補正": "",
    "攻撃補正": "",
    "はりきり補正": "",
    "おやこあい補正": "",
    "防御補正": "",
    "その他の補正": "",
    "Mhalf": "",
    "Mfilter": "",
    "効果": "はがね・どくタイプのポケモンをどく・もうどく状態にできる。"
  },
  {
    "名前": "ふとうのけん",
    "威力補正": "",
    "攻撃補正": "",
    "はりきり補正": "",
    "おやこあい補正": "",
    "防御補正": "",
    "その他の補正": "",
    "Mhalf": "",
    "Mfilter": "",
    "効果": "場に出たとき、こうげきが1段階上がる。"
  },
  {
    "名前": "ふみん",
    "威力補正": "",
    "攻撃補正": "",
    "はりきり補正": "",
    "おやこあい補正": "",
    "防御補正": "",
    "その他の補正": "",
    "Mhalf": "",
    "Mfilter": "",
    "効果": "ねむり状態にならない。"
  },
  {
    "名前": "ふゆう",
    "威力補正": "",
    "攻撃補正": "",
    "はりきり補正": "",
    "おやこあい補正": "",
    "防御補正": "",
    "その他の補正": "じめん無効",
    "Mhalf": "",
    "Mfilter": "",
    "効果": "地面にいない状態になる。"
  },
  {
    "名前": "プラス",
    "威力補正": "",
    "攻撃補正": "攻撃補正",
    "はりきり補正": "",
    "おやこあい補正": "",
    "防御補正": "",
    "その他の補正": "",
    "Mhalf": "",
    "Mfilter": "",
    "効果": "味方の場にプラスかマイナスのポケモンがいる時、とくこうが1.5倍になる。"
  },
  {
    "名前": "フラワーギフト",
    "威力補正": "",
    "攻撃補正": "攻撃補正",
    "はりきり補正": "",
    "おやこあい補正": "",
    "防御補正": "防御補正",
    "その他の補正": "",
    "Mhalf": "",
    "Mfilter": "",
    "効果": "にほんばれのとき、自分と味方のこうげきととくぼうを1.5倍に上げる。"
  },
  {
    "名前": "フラワーベール",
    "威力補正": "",
    "攻撃補正": "",
    "はりきり補正": "",
    "おやこあい補正": "",
    "防御補正": "",
    "その他の補正": "",
    "Mhalf": "",
    "Mfilter": "",
    "効果": "味方の場のくさタイプのポケモンは、相手からランク補正を下げられなくなり、状態異常にもならない。"
  },
  {
    "名前": "フリーズスキン",
    "威力補正": "威力補正",
    "攻撃補正": "",
    "はりきり補正": "",
    "おやこあい補正": "",
    "防御補正": "",
    "その他の補正": "",
    "Mhalf": "",
    "Mfilter": "",
    "効果": "ノーマルタイプのわざがこおりタイプになり、威力が1.2倍になる。"
  },
  {
    "名前": "プリズムアーマー",
    "威力補正": "",
    "攻撃補正": "",
    "はりきり補正": "",
    "おやこあい補正": "",
    "防御補正": "",
    "その他の補正": "",
    "Mhalf": "",
    "Mfilter": "Mfilter",
    "効果": "効果抜群のわざのダメージが0.75倍になる。"
  },
  {
    "名前": "ブレインフォース",
    "威力補正": "",
    "攻撃補正": "",
    "はりきり補正": "",
    "おやこあい補正": "",
    "防御補正": "",
    "その他の補正": "ブレインフォース補正",
    "Mhalf": "",
    "Mfilter": "",
    "効果": "効果抜群のわざの威力が1.25倍になる。"
  },
  {
    "名前": "プレッシャー",
    "威力補正": "",
    "攻撃補正": "",
    "はりきり補正": "",
    "おやこあい補正": "",
    "防御補正": "",
    "その他の補正": "",
    "Mhalf": "",
    "Mfilter": "",
    "効果": "使われる技のPPが1多く減少する。"
  },
  {
    "名前": "フレンドガード",
    "威力補正": "",
    "攻撃補正": "",
    "はりきり補正": "",
    "おやこあい補正": "",
    "防御補正": "",
    "その他の補正": "フレンドガード補正",
    "Mhalf": "",
    "Mfilter": "",
    "効果": "味方へのダメージが0.75倍になる。"
  },
  {
    "名前": "ヘヴィメタル",
    "威力補正": "",
    "攻撃補正": "",
    "はりきり補正": "",
    "おやこあい補正": "",
    "防御補正": "",
    "その他の補正": "",
    "Mhalf": "",
    "Mfilter": "",
    "効果": "重さが2倍になる。"
  },
  {
    "名前": "ヘドロえき",
    "威力補正": "",
    "攻撃補正": "",
    "はりきり補正": "",
    "おやこあい補正": "",
    "防御補正": "",
    "その他の補正": "",
    "Mhalf": "",
    "Mfilter": "",
    "効果": "HPを吸い取るわざを受けたとき、逆にダメージを与える。"
  },
  {
    "名前": "へんげんじざい",
    "威力補正": "",
    "攻撃補正": "",
    "はりきり補正": "",
    "おやこあい補正": "",
    "防御補正": "",
    "その他の補正": "",
    "Mhalf": "",
    "Mfilter": "",
    "効果": "わざを出す直前にそのわざのタイプになる。"
  },
  {
    "名前": "へんしょく",
    "威力補正": "",
    "攻撃補正": "",
    "はりきり補正": "",
    "おやこあい補正": "",
    "防御補正": "",
    "その他の補正": "",
    "Mhalf": "",
    "Mfilter": "",
    "効果": "受けた攻撃技と同じタイプになる。"
  },
  {
    "名前": "ポイズンヒール",
    "威力補正": "",
    "攻撃補正": "",
    "はりきり補正": "",
    "おやこあい補正": "",
    "防御補正": "",
    "その他の補正": "",
    "Mhalf": "",
    "Mfilter": "",
    "効果": "どく・もうどく状態によるダメージを無効化し、HPを1/8回復するようになる。"
  },
  {
    "名前": "ぼうおん",
    "威力補正": "",
    "攻撃補正": "",
    "はりきり補正": "",
    "おやこあい補正": "",
    "防御補正": "",
    "その他の補正": "",
    "Mhalf": "",
    "Mfilter": "",
    "効果": "音のわざを無効化する。"
  },
  {
    "名前": "ほうし",
    "威力補正": "",
    "攻撃補正": "",
    "はりきり補正": "",
    "おやこあい補正": "",
    "防御補正": "",
    "その他の補正": "",
    "Mhalf": "",
    "Mfilter": "",
    "効果": "直接攻撃を受けたとき、相手をどく・まひ・ねむり状態にすることがある。"
  },
  {
    "名前": "ぼうじん",
    "威力補正": "",
    "攻撃補正": "",
    "はりきり補正": "",
    "おやこあい補正": "",
    "防御補正": "",
    "その他の補正": "",
    "Mhalf": "",
    "Mfilter": "",
    "効果": "すなあらし・あられや粉のわざを無効化する。"
  },
  {
    "名前": "ぼうだん",
    "威力補正": "",
    "攻撃補正": "",
    "はりきり補正": "",
    "おやこあい補正": "",
    "防御補正": "",
    "その他の補正": "",
    "Mhalf": "",
    "Mfilter": "",
    "効果": "砲弾系のわざを無効化する。"
  },
  {
    "名前": "ほおぶくろ",
    "威力補正": "",
    "攻撃補正": "",
    "はりきり補正": "",
    "おやこあい補正": "",
    "防御補正": "",
    "その他の補正": "",
    "Mhalf": "",
    "Mfilter": "",
    "効果": "きのみを食べたとき、通常の効果に加えてHPが1/3回復する。"
  },
  {
    "名前": "ほのおのからだ",
    "威力補正": "",
    "攻撃補正": "",
    "はりきり補正": "",
    "おやこあい補正": "",
    "防御補正": "",
    "その他の補正": "",
    "Mhalf": "",
    "Mfilter": "",
    "効果": "直接攻撃を受けたとき、相手をやけど状態にすることがある。タマゴの孵化に必要な歩数が半減する。"
  },
  {
    "名前": "ほろびのボディ",
    "威力補正": "",
    "攻撃補正": "",
    "はりきり補正": "",
    "おやこあい補正": "",
    "防御補正": "",
    "その他の補正": "",
    "Mhalf": "",
    "Mfilter": "",
    "効果": "直接攻撃を受けたとき、お互いがほろびのうた状態になる。"
  },
  {
    "名前": "マイティチェンジ",
    "威力補正": "",
    "攻撃補正": "",
    "はりきり補正": "",
    "おやこあい補正": "",
    "防御補正": "",
    "その他の補正": "",
    "Mhalf": "",
    "Mfilter": "",
    "効果": "手持ちに戻ったとき、マイティフォルムにフォルムチェンジする。"
  },
  {
    "名前": "マイナス",
    "威力補正": "",
    "攻撃補正": "攻撃補正",
    "はりきり補正": "",
    "おやこあい補正": "",
    "防御補正": "",
    "その他の補正": "",
    "Mhalf": "",
    "Mfilter": "",
    "効果": "味方の場にプラスかマイナスのポケモンがいる時、とくこうが1.5倍になる。"
  },
  {
    "名前": "マイペース",
    "威力補正": "",
    "攻撃補正": "",
    "はりきり補正": "",
    "おやこあい補正": "",
    "防御補正": "",
    "その他の補正": "",
    "Mhalf": "",
    "Mfilter": "",
    "効果": "こんらん状態にならない。"
  },
  {
    "名前": "マグマのよろい",
    "威力補正": "",
    "攻撃補正": "",
    "はりきり補正": "",
    "おやこあい補正": "",
    "防御補正": "",
    "その他の補正": "",
    "Mhalf": "",
    "Mfilter": "",
    "効果": "こおり状態にならなくなる。タマゴの孵化に必要な歩数が半減する。"
  },
  {
    "名前": "まけんき",
    "威力補正": "",
    "攻撃補正": "",
    "はりきり補正": "",
    "おやこあい補正": "",
    "防御補正": "",
    "その他の補正": "",
    "Mhalf": "",
    "Mfilter": "",
    "効果": "敵から能力を下げられたとき、こうげきが2段階上がる。"
  },
  {
    "名前": "マジシャン",
    "威力補正": "",
    "攻撃補正": "",
    "はりきり補正": "",
    "おやこあい補正": "",
    "防御補正": "",
    "その他の補正": "",
    "Mhalf": "",
    "Mfilter": "",
    "効果": "攻撃を当てたとき、相手の持ち物を奪う。"
  },
  {
    "名前": "マジックガード",
    "威力補正": "",
    "攻撃補正": "",
    "はりきり補正": "",
    "おやこあい補正": "",
    "防御補正": "",
    "その他の補正": "",
    "Mhalf": "",
    "Mfilter": "",
    "効果": "攻撃以外でのダメージを受けない。"
  },
  {
    "名前": "マジックミラー",
    "威力補正": "",
    "攻撃補正": "",
    "はりきり補正": "",
    "おやこあい補正": "",
    "防御補正": "",
    "その他の補正": "",
    "Mhalf": "",
    "Mfilter": "",
    "効果": "常にマジックコート状態になる。"
  },
  {
    "名前": "マルチスケイル",
    "威力補正": "",
    "攻撃補正": "",
    "はりきり補正": "",
    "おやこあい補正": "",
    "防御補正": "",
    "その他の補正": "",
    "Mhalf": "Mhalf",
    "Mfilter": "",
    "効果": "HPが満タンのとき、受けるダメージが半減する。"
  },
  {
    "名前": "マルチタイプ",
    "威力補正": "",
    "攻撃補正": "",
    "はりきり補正": "",
    "おやこあい補正": "",
    "防御補正": "",
    "その他の補正": "",
    "Mhalf": "",
    "Mfilter": "",
    "効果": "持たせたプレート・Zクリスタルによってフォルムとタイプが変化する。"
  },
  {
    "名前": "ミイラ",
    "威力補正": "",
    "攻撃補正": "",
    "はりきり補正": "",
    "おやこあい補正": "",
    "防御補正": "",
    "その他の補正": "",
    "Mhalf": "",
    "Mfilter": "",
    "効果": "直接攻撃を受けたとき、相手の特性もミイラにする。"
  },
  {
    "名前": "みずがため",
    "威力補正": "",
    "攻撃補正": "",
    "はりきり補正": "",
    "おやこあい補正": "",
    "防御補正": "",
    "その他の補正": "",
    "Mhalf": "",
    "Mfilter": "",
    "効果": "みずタイプの攻撃を受けるとぼうぎょが2段階上がる。"
  },
  {
    "名前": "ミストメイカー",
    "威力補正": "",
    "攻撃補正": "",
    "はりきり補正": "",
    "おやこあい補正": "",
    "防御補正": "",
    "その他の補正": "",
    "Mhalf": "",
    "Mfilter": "",
    "効果": "場の状態をミストフィールドにする。"
  },
  {
    "名前": "みずのベール",
    "威力補正": "",
    "攻撃補正": "",
    "はりきり補正": "",
    "おやこあい補正": "",
    "防御補正": "",
    "その他の補正": "",
    "Mhalf": "",
    "Mfilter": "",
    "効果": "やけど状態にならない。"
  },
  {
    "名前": "みつあつめ",
    "威力補正": "",
    "攻撃補正": "",
    "はりきり補正": "",
    "おやこあい補正": "",
    "防御補正": "",
    "その他の補正": "",
    "Mhalf": "",
    "Mfilter": "",
    "効果": "バトル終了後、あまいミツを拾ってくることがある。"
  },
  {
    "名前": "ミラーアーマー",
    "威力補正": "",
    "攻撃補正": "",
    "はりきり補正": "",
    "おやこあい補正": "",
    "防御補正": "",
    "その他の補正": "",
    "Mhalf": "",
    "Mfilter": "",
    "効果": "相手から受けたランク補正を下げる効果を跳ね返す。"
  },
  {
    "名前": "ミラクルスキン",
    "威力補正": "",
    "攻撃補正": "",
    "はりきり補正": "",
    "おやこあい補正": "",
    "防御補正": "",
    "その他の補正": "",
    "Mhalf": "",
    "Mfilter": "",
    "効果": "相手の変化技の命中率が50%以上の場合は50%になる。"
  },
  {
    "名前": "むしのしらせ",
    "威力補正": "",
    "攻撃補正": "攻撃補正",
    "はりきり補正": "",
    "おやこあい補正": "",
    "防御補正": "",
    "その他の補正": "",
    "Mhalf": "",
    "Mfilter": "",
    "効果": "HPが1/3以下になると、むしタイプのわざで攻撃するときのこうげき・とくこうが1.5倍になる。"
  },
  {
    "名前": "ムラっけ",
    "威力補正": "",
    "攻撃補正": "",
    "はりきり補正": "",
    "おやこあい補正": "",
    "防御補正": "",
    "その他の補正": "",
    "Mhalf": "",
    "Mfilter": "",
    "効果": "毎ターンいずれかのステータスが1段階下がり、2段階上がる。"
  },
  {
    "名前": "メガランチャー",
    "威力補正": "威力補正",
    "攻撃補正": "",
    "はりきり補正": "",
    "おやこあい補正": "",
    "防御補正": "",
    "その他の補正": "",
    "Mhalf": "",
    "Mfilter": "",
    "効果": "はどう系のわざの威力が1.5倍になる。"
  },
  {
    "名前": "メタルプロテクト",
    "威力補正": "",
    "攻撃補正": "",
    "はりきり補正": "",
    "おやこあい補正": "",
    "防御補正": "",
    "その他の補正": "",
    "Mhalf": "",
    "Mfilter": "",
    "効果": "相手からランク補正を下げられない。"
  },
  {
    "名前": "メロメロボディ",
    "威力補正": "",
    "攻撃補正": "",
    "はりきり補正": "",
    "おやこあい補正": "",
    "防御補正": "",
    "その他の補正": "",
    "Mhalf": "",
    "Mfilter": "",
    "効果": "直接攻撃を受けたとき、相手をメロメロにすることがある。"
  },
  {
    "名前": "めんえき",
    "威力補正": "",
    "攻撃補正": "",
    "はりきり補正": "",
    "おやこあい補正": "",
    "防御補正": "",
    "その他の補正": "",
    "Mhalf": "",
    "Mfilter": "",
    "効果": "どく、もうどく状態にならない。"
  },
  {
    "名前": "もうか",
    "威力補正": "",
    "攻撃補正": "攻撃補正",
    "はりきり補正": "",
    "おやこあい補正": "",
    "防御補正": "",
    "その他の補正": "",
    "Mhalf": "",
    "Mfilter": "",
    "効果": "HPが1/3以下になると、ほのおタイプのわざで攻撃するときのこうげき・とくこうが1.5倍になる。"
  },
  {
    "名前": "ものひろい",
    "威力補正": "",
    "攻撃補正": "",
    "はりきり補正": "",
    "おやこあい補正": "",
    "防御補正": "",
    "その他の補正": "",
    "Mhalf": "",
    "Mfilter": "",
    "効果": "相手の使ったアイテムを拾う。バトル終了後アイテムを拾うことがある。"
  },
  {
    "名前": "もふもふ",
    "威力補正": "",
    "攻撃補正": "",
    "はりきり補正": "",
    "おやこあい補正": "",
    "防御補正": "",
    "その他の補正": "もふもふ補正",
    "Mhalf": "Mhalf",
    "Mfilter": "",
    "効果": "受ける直接攻撃のダメージが0.5倍、ほのおわざのダメージが2倍になる。"
  },
  {
    "名前": "もらいび",
    "威力補正": "",
    "攻撃補正": "攻撃補正",
    "はりきり補正": "",
    "おやこあい補正": "",
    "防御補正": "",
    "その他の補正": "ほのお無効",
    "Mhalf": "",
    "Mfilter": "",
    "効果": "ほのおタイプのわざを無効化し、その後自分がほのおわざを使う時のこうげき・とくこうが1.5倍になる。"
  },
  {
    "名前": "やるき",
    "威力補正": "",
    "攻撃補正": "",
    "はりきり補正": "",
    "おやこあい補正": "",
    "防御補正": "",
    "その他の補正": "",
    "Mhalf": "",
    "Mfilter": "",
    "効果": "ねむり状態にならない。"
  },
  {
    "名前": "ゆうばく",
    "威力補正": "",
    "攻撃補正": "",
    "はりきり補正": "",
    "おやこあい補正": "",
    "防御補正": "",
    "その他の補正": "",
    "Mhalf": "",
    "Mfilter": "",
    "効果": "ひんしになったとき、相手に1/4のダメージを与える。"
  },
  {
    "名前": "ゆきかき",
    "威力補正": "",
    "攻撃補正": "",
    "はりきり補正": "",
    "おやこあい補正": "",
    "防御補正": "",
    "その他の補正": "",
    "Mhalf": "",
    "Mfilter": "",
    "効果": "あられ/ゆきのとき、すばやさが2倍になる。"
  },
  {
    "名前": "ゆきがくれ",
    "威力補正": "",
    "攻撃補正": "",
    "はりきり補正": "",
    "おやこあい補正": "",
    "防御補正": "",
    "その他の補正": "",
    "Mhalf": "",
    "Mfilter": "",
    "効果": "あられ/ゆきのとき、回避率が1.25倍になる。"
  },
  {
    "名前": "ゆきふらし",
    "威力補正": "",
    "攻撃補正": "",
    "はりきり補正": "",
    "おやこあい補正": "",
    "防御補正": "",
    "その他の補正": "",
    "Mhalf": "",
    "Mfilter": "",
    "効果": "場をあられ4-8/9にする。"
  },
  {
    "名前": "ようりょくそ",
    "威力補正": "",
    "攻撃補正": "",
    "はりきり補正": "",
    "おやこあい補正": "",
    "防御補正": "",
    "その他の補正": "",
    "Mhalf": "",
    "Mfilter": "",
    "効果": "にほんばれのとき、すばやさが2倍になる。"
  },
  {
    "名前": "ヨガパワー",
    "威力補正": "",
    "攻撃補正": "攻撃補正",
    "はりきり補正": "",
    "おやこあい補正": "",
    "防御補正": "",
    "その他の補正": "",
    "Mhalf": "",
    "Mfilter": "",
    "効果": "こうげきが2倍になる。"
  },
  {
    "名前": "よちむ",
    "威力補正": "",
    "攻撃補正": "",
    "はりきり補正": "",
    "おやこあい補正": "",
    "防御補正": "",
    "その他の補正": "",
    "Mhalf": "",
    "Mfilter": "",
    "効果": "相手の持つわざが1つ分かる。"
  },
  {
    "名前": "よびみず",
    "威力補正": "",
    "攻撃補正": "",
    "はりきり補正": "",
    "おやこあい補正": "",
    "防御補正": "",
    "その他の補正": "みず無効",
    "Mhalf": "",
    "Mfilter": "",
    "効果": "みずわざの対象を自分にし、無効化してとくこうを1段階上げる。"
  },
  {
    "名前": "よわき",
    "威力補正": "",
    "攻撃補正": "攻撃補正",
    "はりきり補正": "",
    "おやこあい補正": "",
    "防御補正": "",
    "その他の補正": "",
    "Mhalf": "",
    "Mfilter": "",
    "効果": "HPが半分以下になると、こうげきととくこうが半分になる。"
  },
  {
    "名前": "ライトメタル",
    "威力補正": "",
    "攻撃補正": "",
    "はりきり補正": "",
    "おやこあい補正": "",
    "防御補正": "",
    "その他の補正": "",
    "Mhalf": "",
    "Mfilter": "",
    "効果": "重さが半分になる。"
  },
  {
    "名前": "リーフガード",
    "威力補正": "",
    "攻撃補正": "",
    "はりきり補正": "",
    "おやこあい補正": "",
    "防御補正": "",
    "その他の補正": "",
    "Mhalf": "",
    "Mfilter": "",
    "効果": "にほんばれのときに状態異常にならない。"
  },
  {
    "名前": "リベロ",
    "威力補正": "",
    "攻撃補正": "",
    "はりきり補正": "",
    "おやこあい補正": "",
    "防御補正": "",
    "その他の補正": "",
    "Mhalf": "",
    "Mfilter": "",
    "効果": "わざを出す直前にそのわざのタイプになる。"
  },
  {
    "名前": "リミットシールド",
    "威力補正": "",
    "攻撃補正": "",
    "はりきり補正": "",
    "おやこあい補正": "",
    "防御補正": "",
    "その他の補正": "",
    "Mhalf": "",
    "Mfilter": "",
    "効果": "HPが半分より多いとメテノのフォルムが変わる。"
  },
  {
    "名前": "りゅうのあぎと",
    "威力補正": "",
    "攻撃補正": "攻撃補正",
    "はりきり補正": "",
    "おやこあい補正": "",
    "防御補正": "",
    "その他の補正": "",
    "Mhalf": "",
    "Mfilter": "",
    "効果": "ドラゴンタイプのわざで攻撃するとき、こうげき・とくこうが1.5倍になる。"
  },
  {
    "名前": "りんぷん",
    "威力補正": "",
    "攻撃補正": "",
    "はりきり補正": "",
    "おやこあい補正": "",
    "防御補正": "",
    "その他の補正": "",
    "Mhalf": "",
    "Mfilter": "",
    "効果": "攻撃技の追加効果を受けない。"
  },
  {
    "名前": "レシーバー",
    "威力補正": "",
    "攻撃補正": "",
    "はりきり補正": "",
    "おやこあい補正": "",
    "防御補正": "",
    "その他の補正": "",
    "Mhalf": "",
    "Mfilter": "",
    "効果": "味方がひんしになったとき、そのポケモンと同じ特性になる。"
  },
  {
    "名前": "わざわいのうつわ",
    "威力補正": "",
    "攻撃補正": "攻撃補正",
    "はりきり補正": "",
    "おやこあい補正": "",
    "防御補正": "",
    "その他の補正": "",
    "Mhalf": "",
    "Mfilter": "",
    "効果": "この特性のポケモン以外全員のとくこうが3/4倍になる。"
  },
  {
    "名前": "わざわいのおふだ",
    "威力補正": "",
    "攻撃補正": "攻撃補正",
    "はりきり補正": "",
    "おやこあい補正": "",
    "防御補正": "",
    "その他の補正": "",
    "Mhalf": "",
    "Mfilter": "",
    "効果": "この特性のポケモン以外全員のこうげきが3/4倍になる。"
  },
  {
    "名前": "わざわいのたま",
    "威力補正": "",
    "攻撃補正": "",
    "はりきり補正": "",
    "おやこあい補正": "",
    "防御補正": "防御補正",
    "その他の補正": "",
    "Mhalf": "",
    "Mfilter": "",
    "効果": "この特性のポケモン以外全員のとくぼうが3/4倍になる。"
  },
  {
    "名前": "わざわいのつるぎ",
    "威力補正": "",
    "攻撃補正": "",
    "はりきり補正": "",
    "おやこあい補正": "",
    "防御補正": "防御補正",
    "その他の補正": "",
    "Mhalf": "",
    "Mfilter": "",
    "効果": "この特性のポケモン以外全員のぼうぎょが3/4倍になる。"
  },
  {
    "名前": "わたげ",
    "威力補正": "",
    "攻撃補正": "",
    "はりきり補正": "",
    "おやこあい補正": "",
    "防御補正": "",
    "その他の補正": "",
    "Mhalf": "",
    "Mfilter": "",
    "効果": "攻撃を受けると自分以外のポケモンのすばやさを1段階下げる。"
  },
  {
    "名前": "わるいてぐせ",
    "威力補正": "",
    "攻撃補正": "",
    "はりきり補正": "",
    "おやこあい補正": "",
    "防御補正": "",
    "その他の補正": "",
    "Mhalf": "",
    "Mfilter": "",
    "効果": "直接攻撃を受けたとき、相手の道具を奪う。"
  }
]